Workbook
Name Requerimientos_Instrumental: 'REQ. FUN. GEN'!$C$8

Sheet GENERAL
K5: RESUMEN REQUERIMIENTOS
F6: TOTAL | G6: CUMPLE | H6: NO CUMPLE
C7: * Requisitos de usuario | F7: ='REQ. USUARIO'!E19 -> 52 | G7: ='REQ. USUARIO'!C16 -> 38 | H7: ='REQ. USUARIO'!G16 -> 14
K8: TOTAL | O8: CUMPLIDOS | S8: NO CUMPLIDOS
C9: * Requisitos funcionales | F9: ='REQ. FUN. GEN'!N26 -> 356 | G9: ='REQ. FUN. GEN'!L23 -> 318 | H9: ='REQ. FUN. GEN'!P23 -> 38 | K9: =SUM(F7,F9,F11) -> 725 | O9: =SUM(G7,G9,G11) -> 647 | S9: =SUM(H7,H9,H11) -> 78
C11: * Requisitos no funcionales | F11: ='REQ. NO FUN. GEN'!N26 -> 317 | G11: ='REQ. NO FUN. GEN'!L23 -> 291 | H11: ='REQ. NO FUN. GEN'!P23 -> 26
C14: Porcentaje real | E14: =O9/K9 -> 0.89241379
C16: Inventario Transacciones

Sheet REQ. USUARIO
G3: Cumple | H3: No cumple
C4: * Requisitos funcionales | G4: =COUNTIF('REQ. FUN'!M:M, "x") -> 24 | H4: =COUNTIF('REQ. FUN'!N:N, "x") -> 7
L5: Volver
C6: * Requisitos no funcionales | G6: =COUNTIF('REQ. NO FUN'!M:M, "x") -> 14 | H6: =COUNTIF('REQ. NO FUN'!N:N, "x") -> 7
C11: REQUERIMIENTOS USUARIO
C15: Cumplidos | G15: No cumplidos
C16: =SUM(G4:G6) -> 38 | G16: =SUM(H4:H6) -> 14
E18: Implementados
E19: =SUM(C16,G16) -> 52

Sheet REQ. FUN. GEN
F2: Cumple | G2: No cumple
C3: * Requerimientos Inicio / Landing | F3: =COUNTIF('PAG. WEB - Landing FUN.'!M:M, "x") -> 21 | G3: =COUNTIF('PAG. WEB - Landing FUN.'!N:N, "x") -> 7
C4: * Requerimientos Inicio de sesión | F4: =COUNTIF('Inicio de sesión FUN.'!M:M, "x") -> 35 | G4: =COUNTIF('Inicio de sesión FUN.'!N:N, "x") -> 2
C5: * Requerimientos Registro | F5: =COUNTIF('Registro FUN.'!M:M, "x") -> 28 | G5: =COUNTIF('Registro FUN.'!N:N, "x") -> 2
C6: * Requerimientos Panel Administrador | F6: =COUNTIF('Panel Admin FUN.'!M:M, "x") -> 42 | G6: =COUNTIF('Panel Admin FUN.'!N:N, "x") -> 4
C7: * Requerimientos Información Personal | F7: =COUNTIF('Inf. Personal FUN.'!M:M, "x") -> 31 | G7: =COUNTIF('Inf. Personal FUN.'!N:N, "x") -> 1
C8: * Requerimientos Instrumental | F8: =COUNTIF('Instrumental FUN.'!M:M, "x") -> 53 | G8: =COUNTIF('Instrumental FUN.'!N:N, "x") -> 2
C9: * Requerimientos Materia Prima | F9: =COUNTIF('Materia prima FUN.'!M:M, "x") -> 41 | G9: =COUNTIF('Materia prima FUN.'!N:N, "x") -> 1
C10: * Requerimientos Productos | F10: =COUNTIF('Productos FUN'!M:M, "x") -> 13 | G10: =COUNTIF('Productos FUN'!N:N, "x") -> 0
C11: * Requerimientos Finanzas | F11: =COUNTIF('Finanzas FUN'!M:M, "x") -> 9 | G11: =COUNTIF('Productos FUN'!N:N, "x") -> 0
C12: * Requerimientos Historial | F12: =COUNTIF('Historial FUN'!M:M, "x") -> 21 | G12: =COUNTIF('Historial FUN'!N:N, "x") -> 3
C13: * Requerimientos Clientes | F13: =COUNTIF('Clientes FUN'!M:M, "x") -> 7 | G13: =COUNTIF('Clientes FUN'!N:N, "x") -> 3
C14: * Requerimientos Facturación | F14: =COUNTIF('Facturación FUN.'!M:M, "x") -> 9 | G14: =COUNTIF('Facturación FUN.'!N:N, "x") -> 1
C17: * Gestión de Usuarios y Autenticación | F17: =COUNTIF('Gestión Usuarios FUN.'!M:M, "x") -> 6 | G17: =COUNTIF('Gestión Usuarios FUN.'!N:N, "x") -> 4
C18: * Gestión de Permisos y Menús | F18: =COUNTIF('Permisos y Menús FUN.'!M:M, "x") -> 2 | G18: =COUNTIF('Permisos y Menús FUN.'!N:N, "x") -> 8 | L18: REQUERIMIENTOS FUNCIONALES
L22: Cumplidos | P22: No cumplidos
L23: =SUM(F3:F14,F17:F18,P3:P7) -> 318 | P23: =SUM(G3:G14,G17:G18,Q3:Q7) -> 38
C24: Volver
N25: Implementados
N26: =SUM(L23,P23) -> 356

Sheet REQ. NO FUN. GEN
F2: Cumple | G2: No cumple
C3: * Requerimientos Inicio / Landing | F3: =COUNTIF('PAG. WEB - Landing NO FUN.'!M:M, "x") -> 28 | G3: =COUNTIF('PAG. WEB - Landing NO FUN.'!N:N, "x") -> 3
C4: * Requerimientos Inicio de sesión | F4: =COUNTIF('Inicio de sesión NO FUN.'!M:M, "x") -> 16 | G4: =COUNTIF('Inicio de sesión NO FUN.'!N:N, "x") -> 4
C5: * Requerimientos Registro | F5: =COUNTIF('Registro NO FUN.'!M:M, "x") -> 21 | G5: =COUNTIF('Registro NO FUN.'!N:N, "x") -> 2
C6: * Requerimientos Panel Administrador | F6: =COUNTIF('Panel Admin NO FUN.'!M:M, "x") -> 33 | G6: =COUNTIF('Panel Admin NO FUN.'!N:N, "x") -> 2
C7: * Requerimientos Información Personal | F7: =COUNTIF('Inf. Personal NO FUN.'!M:M, "x") -> 0 | G7: =COUNTIF('Inf. Personal NO FUN.'!N:N, "x") -> 0
C8: * Requerimientos Instrumental | F8: =COUNTIF('Instrumental NO FUN.'!M:M, "x") -> 37 | G8: =COUNTIF('Instrumental NO FUN.'!N:N, "x") -> 1
C9: * Requerimientos Materia Prima | F9: =COUNTIF('Materia prima NO FUN.'!M:M, "x") -> 13 | G9: =COUNTIF('Materia prima NO FUN.'!N:N, "x") -> 1
C10: * Requerimientos Productos | F10: =COUNTIF('Productos NO FUN'!M:M, "x") -> 27 | G10: =COUNTIF('Productos NO FUN'!N:N, "x") -> 0
C11: * Requerimientos Finanzas | F11: =COUNTIF('Finanzas NO FUN'!M:M, "x") -> 27 | G11: =COUNTIF('Finanzas NO FUN'!N:N, "x") -> 0
C12: * Requerimientos Historial | F12: =COUNTIF('Historial NO FUN.'!M:M, "x") -> 82 | G12: =COUNTIF('Historial NO FUN.'!N:N, "x") -> 0
C13: * Requerimientos Clientes | F13: =COUNTIF('Clientes NO FUN.'!M:M, "x") -> 3 | G13: =COUNTIF('Clientes NO FUN.'!N:N, "x") -> 2
C14: * Requerimientos Facturación | F14: =COUNTIF('Facturación NO FUN.'!M:M, "x") -> 2 | G14: =COUNTIF('Facturación NO FUN.'!N:N, "x") -> 3
C17: * Gestión de Usuarios y Autenticación | F17: =COUNTIF('Gestión Usuarios NO FUN.'!M:M, "x") -> 2 | G17: =COUNTIF('Gestión Usuarios NO FUN.'!N:N, "x") -> 3
C18: * Gestión de Permisos y Menús | F18: =COUNTIF('Permisos y Menús NO FUN.'!M:M, "x") -> 0 | G18: =COUNTIF('Permisos y Menús NO FUN.'!N:N, "x") -> 5 | L18: REQUERIMIENTOS NO FUNCIONALES
L22: Cumplidos | P22: No cumplidos
L23: =SUM(F3:F14,F17:F18,) -> 291 | P23: =SUM(G3:G14,G17:G18,Q3:Q7) -> 26
N25: Implementados
N26: =SUM(L23,P23) -> 317
C29: Volver

Sheet REQ. FUN
B2: SI | C2: Marque con una equis (X) si el sistema no cumple con la función descrita | T2: Volver
B3: NO | C3: Marque con una equis (X) si el sistema cumple con la función descrita
B4: ADI | C4: Marque con una equis (X) si el sistema debe adicionar la función descrita
B5: Observaciones: | D5: Espacio para complementar respuestas
B7: P
M8: Nivel de cumplimiento | P8: OBSERVACIONES
E9: REQUERIMIENTOS FUNCIONALES SPECIALIZED | M9: SI | N9: NO | O9: ADI
C11: Gestión de productos
B12: 1 | C12: El sistema contará con un módulo de gestión de catálogo. | M12: x
B13: 2 | C13: El sistema debe permitir actualizar la informacion de los productos disponibles. | M13: x
B14: 3 | C14: El sistema debe permitir eliminar los productos que ya no se deseen mostrar en el catálogo. | M14: x
C16: Almacenamiento de instrumental disponible
B17: 5 | C17: El sistema debe mostrar en tiempo real el stock disponible de cada producto. | M17: x
B18: 6 | C18: El sistema debe tener alertas automáticas cuando el stock de un producto sea inferior al normal establecido. | M18: x
C20: Control de inventario
B21: 8 | C21: El sistema debe registrar salidas de productos del inventario con detalles como fecha, cantidad y motivo (por ejemplo, venta o pérdida). | M21: x
B22: 9 | C22: Generar reportes automáticos de inventario para análisis periódico (Como los productos que más se vendieron en un mes). | M22: x
B23: 10 | C23: Permitir registrar información sobre la materia prima utilizada en la fabricación de productos, como proveedores, cantidades disponibles, costos unitarios y fechas de adquisición. | M23: x
C25: Gestión de proveedores
B26: 11 | C26: Registrar información detallada de proveedores, como nombre, dirección, teléfono, correo electrónico, productos suministrados y condiciones de compra. | M26: x
B27: 12 | C27: Permitir eliminar proveedores a los cuales ya no se les pide materia prima, o dejaron de proveer esta misma. | M27: x
B28: 13 | C28: Permitir actualizar proveedores en caso que se tenga que actualizar algún dato de estos. | M28: x
B29: 14 | C29: Incluir funcionalidades para realizar búsquedas rápidas y filtrar por nombre o tipo de producto suministrado. | N29: x
C31: Gestión de clientes
B32: 15 | C32: Permitir almacenar información de clientes, incluyendo nombre, tipo de cliente (profesional, estudiante, etc.), dirección, teléfono y correo electrónico. | M32: x
B33: 17 | C33: Permitir segmentar clientes según su tipo (estudiante, profesional, etc.) para personalizar ofertas y analizar patrones de compra. | N33: x
C35: Facturación
B36: 18 | C36: Generar facturas automáticamente al confirmar una venta, incluyendo información del cliente, productos vendidos, cantidades, precios unitarios, impuestos y totales. | M36: x
B37: 19 | C37: El sistema debe generar automáticamente una factura en formato PDF al confirmar una venta, El PDF deberá estar disponible para visualización, descarga e impresión. | M37: x
C39: Reportes
B40: 20 | C40: Generar reportes sobre ventas, inventario, ingresos, clientes y proveedores. | N40: x
B41: 21 | C41: Permitir la personalización de reportes para incluir filtros por fecha, categorías de productos, etc. | M41: x
C43: Gestión de precios
B44: 22 | C44: Permitir actualizar precios de productos. | M44: x
B45: 23 | C45: Implementar promociones o descuentos temporales con fechas de inicio y fin. | N45: x
C48: Gestión de devoluciones
B49: 25 | C49: Registrar devoluciones de productos, especificando el motivo, la cantidad devuelta y las acciones tomadas (reemplazo, reembolso, reparación). | M49: x
C52: Gestión de usuarios
B53: 27 | C53: Permitir la creación de cuentas de usuario (administrador o cliente). | M53: x
B54: 28 | C54: Implementar autenticación segura mediante contraseñas encriptadas y opciones de recuperación. | M54: x
C56: Gestión de empleados
B57: 29 | C57: Registrar información del personal, incluyendo nombre, cargo, dirección, teléfono, correo electrónico y fecha de ingreso. | M57: x
B58: 30 | C58: El sistema debe permitir eliminar registros de empleados que ya no estén vinculados a la empresa. | M58: x
B59: 31 | C59: El sistema debe permitir actualizar registros de empleados según lo necesite el usuario. | M59: x
B60: 32 | C60: Incluir un módulo para registrar y gestionar informes médicos del personal, asegurando la confidencialidad. | N60: x
C62: Otros
B63: 33 | C63: Implementar un sistema de búsquedas y filtros avanzados para listar materias primas y servicios ofrecidos por un proveedor específico. | N63: x
B64: 34 | C64: El sistema debe llevar los colores institucionales (verde, blanco y azul). | M64: x
B65: 35 | C65: Registrar un log de actividades críticas (ej: eliminación de productos, cambios de precios) con usuario, fecha y hora, para trazabilidad. | N65: x
B66: 36 | C66: Implementar interfaz en al menos 2 idiomas (español/inglés), con posibilidad de añadir más en el futuro. | M66: x

Sheet REQ. NO FUN
A1: y e
B2: SI | C2: Marque con una equis (X) si el sistema no cumple con la función descrita | U2: Volver
B3: NO | C3: Marque con una equis (X) si el sistema cumple con la función descrita
B4: ADI | C4: Marque con una equis (X) si el sistema debe adicionar la función descrita
B5: Observaciones: | D5: Espacio para complementar respuestas
B7: P
M8: Nivel de cumplimiento | P8: OBSERVACIONES
D9: REQUERIMIENTOS NO FUNCIONALES SPECIALIZED | M9: SI | N9: NO | O9: ADI
C11: Seguridad
B12: 1 | C12: Proteger los datos de clientes, empleados y proveedores mediante algoritmos de encriptación. | M12: x
B13: 2 | C13: Encriptación de la contraseña del usuario del sistema. | M13: x
B14: 3 | C14: Implementar medidas contra ataques como SQL Injection. | M14: x
B15: 5 | C15: Si un usuario falla 3 veces al ingresar su contraseña, su cuenta se bloquea temporalmente. | N15: x
B16: 6 | C16: Accesos restringidos: Solo los jefes o administradores pueden ver informes médicos de empleados. | N16: x
C18: Desempeño
B19: 7 | C19: El tiempo de respuesta del sistema debe ser inferior a 3 segundos en operaciones comunes como la realización de búsquedas. | M19: x
B20: 8 | C20: Reportes rápidos: Generar un reporte de ventas mensual no debe tardar más de 10 segundos. | M20: x
C22: Escalabilidad
B23: 9 | C23: El sistema debe ser capaz de manejar un aumento en el número de usuarios. | M23: x
B24: 10 | C24: El sistema debe ser capaz de manejar un aumento en el número de productos sin afectar el rendimiento. | N24: x
B25: 11 | C25: El sistema debe ser capaz de manejar un aumento en el número de transacciones sin afectar el rendimiento. | N25: x
C27: Usabilidad
B28: 12 | C28: La interfaz del sistema debe ser intuitiva. | M28: x
B29: 13 | C29: La interfaz del sistema debe ser fácil de usar. | M29: x
C31: Compatibilidad
B32: 15 | C32: El sistema debe ser compatible con los principales navegadores web (Chrome, Firefox, Edge, Safari). | M32: x
B33: 16 | C33: Debe ser accesible desde dispositivos móviles, tabletas y computadoras de escritorio. | M33: x
B34: 17 | C34: Realizar copias de seguridad automáticas diariamente y permitir restauración rápida en caso de fallas. | N34: x
B35: 18 | C35: El sistema cumple con normativas locales e internacionales, como las leyes de protección de datos personales. | M35: x
C37: Mantenimiento
B38: 19 | C38: Restaurar información: Si se pierden datos, poder recuperarlos desde la última copia de seguridad. | N38: x
B39: 20 | C39: El sistema debe mostrar mensajes claros cuando hay errores (ej: "No se pudo guardar. Revise su conexión a internet"). | M39: x
C41: Otros
B42: 22 | C42: Leyes de privacidad: Cumplir con normas de protección de datos (ej: no compartir información de clientes sin permiso). | M42: x
B43: 23 | C43: El sistema debe poder imprimir facturas o reportes sin configurar nada extra. | M43: x
B44: 24 | C44: Logo visible: Mostrar el logo de la empresa en todas las pantallas importantes (facturas, reportes). | N44: x

Sheet PAG. WEB - Landing FUN.
B2: SI | C2: Marque con una equis (X) si el sistema no cumple con la función descrita | T2: Volver
B3: NO | C3: Marque con una equis (X) si el sistema cumple con la función descrita
B4: ADI | C4: Marque con una equis (X) si el sistema debe adicionar la función descrita
B5: Observaciones: | D5: Espacio para complementar respuestas
B7: P
M8: Nivel de cumplimiento | P8: OBSERVACIONES
D9: REQUERIMIENTOS GENERALES FUNCIONALES DE LA PÁGINA WEB - LANDING | M9: SI | N9: NO | O9: ADI
B12: 1 | C12: Mostrar menú superior con opciones de navegación | M12: x
B13: 2 | C13: Mostrar botón "Ingresar" en esquina superior derecha | M13: x
B14: 3 | C14: Búsqueda Dinámica: Filtrado de productos en tiempo real al ingresar caracteres (ej: "li"). | M14: x
B15: 4 | C15: Auto-cierre de Secciones: Al limpiar la búsqueda, las secciones desplegadas deben cerrarse solas. | M15: x
B16: 5 | C16: Controlador de Limpieza: Botón dedicado para resetear el campo de búsqueda de forma instantánea. | M16: x
B17: 6 | C17: Navegación por Tabs: Selección de categorías mediante botones de menú superior. | M17: x
B18: 7 | C18: Despliegue de Información: Mostrar descripción y productos al hacer clic en una categoría. | M18: x
B19: 8 | C19: Gestión de Cookies: Desplegar modal informativo antes de permitir el acceso al Login. | M19: x
B20: 9 | C20: Lógica de Redirección: El sistema debe redirigir al login tras interactuar con el modal de cookies. | M20: x
B21: 10 | C21: Visualización de Kits: Listado de instrumentos agrupados por especialidad dental. | M21: x
B22: 11 | C22: Botón "Ingresar": Enlace funcional hacia el módulo de autenticación. | M22: x
B23: 12 | C23: Visualización de Imágenes de Kits: Mostrar fotografías reales de los productos en el hover. | M23: x
... B27: 16 | C27: Mostrar mensaje de bienvenida al usuario. | M27: x
B28: 17 | C28: Carrusel de productos destacados. | N28: x
B29: 18 | C29: Barra de búsqueda en header. | M29: x
B30: 20 | C30: Enlace directo a WhatsApp de ventas. | M30: x
B31: 21 | C31: Etiqueta "Nuevo" en productos recientes. | N31: x
B32: 22 | C32: Botón "Volver arriba" en scroll. | N32: x | R32: Por el momento la página no tiene movimientos scroll
B33: 23 | C33: Vista rápida de productos. | M33: x
B34: 24 | C34: Sección de noticias o blog. | N34: x
B35: 26 | C35: Filtro por tipo de material (acero/liviano). | N35: x
B36: 27 | C36: Filtro por especialización dental. | M36: x
B37: 28 | C37: Descarga de catálogo en PDF. | N37: x
B38: 29 | C38: Vista de productos agotados. | N38: x
B39: 30 | C39: Estado de Carga: Mostrar nombres de productos y descripciones base incluso si la imagen falla. | M39: x

Sheet PAG. WEB - Landing NO FUN.
B2: SI | C2: Marque con una equis (X) si el sistema no cumple con la función descrita | V2: Volver
B3: NO | C3: Marque con una equis (X) si el sistema cumple con la función descrita
B4: ADI | C4: Marque con una equis (X) si el sistema debe adicionar la función descrita
B5: Observaciones: | D5: Espacio para complementar respuestas
B7: P
M8: Nivel de cumplimiento | P8: OBSERVACIONES
D9: REQUERIMIENTOS GENERALES NO FUNCIONALES DE LA PÁGINA WEB - LANDING | M9: SI | N9: NO | O9: ADI
B12: 1 | C12: Página carga en menos de 5 segundos. | M12: x | R12: Navegación con teclado posible
B13: 2 | C13: Colores verde, blanco y azul corporativos. | M13: x | R13: Seguridad básica contra hackers
B14: 3 | C14: Textos legibles y tamaño adecuado. | M14: x | R14: Contraseñas encriptadas en base de datos
B15: 4 | C15: Mostrar header con logo de la empresa. | M15: x
B16: 5 | C16: Identidad Corporativa: Header con degradado lineal (linear-gradient) verde y azul. | M16: x
B17: 6 | C17: Cambio de color de fondo y texto al pasar el mouse por los menús. | M17: x
B18: 7 | C18: Efecto de Elevación: Las cartas de producto deben subir (translateY) al pasar el mouse. | M18: x
B19: 8 | C19: Sombreado Dinámico: Aparición de sombras (box-shadow) profundas en elementos activos. | M19: x
B20: 9 | C20: Transiciones Suaves: Los efectos visuales deben durar 0.3s para mejorar la fluidez (UX). | M20: x
B21: 10 | C21: Cambio de brillo/oscuridad en el botón "Ingresar" al interactuar. | M21: x
B22: 11 | C22: Adaptabilidad (Responsive): Uso de Media Queries para que la web funcione en móviles. | M22: x
B23: 12 | C23: Arquitectura Limpia: Separación total de estilos (CSS) y estructura (HTML). Archivos independientes. | M23: x
B24: 13 | C24: Iconografía Estándar: Integración con FontAwesome para íconos del sistema. | M24: x | R24: iconos extraidos de otra web
B25: 14 | C25: Interfaz Intuitiva: Barra de búsqueda centrada y de fácil acceso visual. | M25: x
B26: 15 | C26: Iconografía Específica: Ícono de "escoba" para la limpieza de búsqueda. | N26: x
B27: 16 | C27: Imágenes no pixeladas. | M27: x
B28: 17 | C28: Formularios con validación básica. | M28: x
B29: 18 | C29: Links funcionan correctamente. | M29: x
B30: 19 | C30: Página no se cae con muchos usuarios. | M30: x | R30: Datos de clientes protegidos
B31: 20 | C31: Funciona en Edge y Safari también. | M31: x
B32: 21 | C32: Cambio de cursor a 'pointer' en botones y cartas. | M32: x
B33: 22 | C33: Suavizado de bordes: Interfaz con esquinas redondeadas para estética moderna. | M33: x
B34: 23 | C34: Optimización de carga: Scripts ubicados al final del body para mayor velocidad. | M34: x
B35: 24 | C35: Jerarquía visual: Títulos destacados con colores institucionales. | M35: x
B36: 25 | C36: Imágenes optimizadas para web. | N36: x
B37: 26 | C37: Formularios con mensajes de error claros. | M37: x
B38: 28 | C38: Compatible con lectores de pantalla. | N38: x
B39: 29 | C39: Cumplimiento ley de protección de datos. | M39: x
B40: 31 | C40: Escalable para más productos. | M40: x
B41: 32 | C41: Fácil de actualizar contenido. | M41: x
B42: 33 | C42: No requiere software especial. | M42: x

Sheet Inicio de sesión FUN.
B2: SI | C2: Marque con una equis (X) si el sistema no cumple con la función descrita | V2: Volver
B3: NO | C3: Marque con una equis (X) si el sistema cumple con la función descrita
B4: ADI | C4: Marque con una equis (X) si el sistema debe adicionar la función descrita
B5: Observaciones: | D5: Espacio para complementar respuestas
B7: P
M8: Nivel de cumplimiento | P8: OBSERVACIONES
D9: REQUERIMIENTOS FUNCIONALES DEL INICIO DE SESIÓN | M9: SI | N9: NO | O9: ADI
B12: 1 | C12: Mostrar formulario con campos "Usuario" y "Contraseña". | M12: x | R12: olvidar contraseña + olvidé usuario
B13: 2 | C13: Logo corporativo visible en pantalla de login. | N13: x
B14: 3 | C14: Campo contraseña con ocultación de caracteres. | M14: x
B15: 5 | C15: El sistema debe mostrar el panel de inicio de sesión. | M15: x
B16: 6 | C16: Botón "INICIAR SESIÓN" que envía datos al servidor. | M16: x
B17: 8 | C17: Enlace "¿Olvidaste tu contraseña?" funcional. | M17: x
B18: 9 | C18: Al dar click en "¿Olvidaste tu contraseña?" el sistema debe abrir un modal con el título "Recuperar Contraseña" y el mensaje "Ingresa tu nombre de usuario para buscar tu cuenta.". | M18: x
B19: 10 | C19: El modal debe mostrar un campo para ingresar el "Nombre de usuario" y si se ingresa un dato debe proceder a buscar el registro en el sistema, junto con el botón "Buscar" funcional. | M19: x
B20: 11 | C20: Si al dar click en el botón "Buscar" el campo está vacío el sistema debe mostrar un modal con el mensaje "Ingresa tu usuario" y un botón aceptar. | M20: x
B21: 12 | C21: Si al dar click en el botón "Buscar" y el campo contiene un user incorrecto, el sistema debe mostrar un modal con el mensaje "Usuario no encontrado" y un botón aceptar. | M21: x
B22: 13 | C22: El sistema debe verificar si el user ingresado corresponde a un usuario ya registrado, si el user no corresponde a un usuario el sistema debe mostrar un cuadro de modal que indique que el usuario no se encuentra. | M22: x
B23: 14 | C23: Si el user sí está registrado, el sistema debe abrir un nuevo modal con el título "Elige un método" y el mensaje "¿Cómo quieres recibir tu código de recuperación?". | M23: x
B24: 15 | C24: El modal debe mostrar dos opciones, la opción "Enviar a Email (correo_registrado@dominio.com)" y la opción "Enviar SMS (Télefono_registrado)". | M24: x
B25: 16 | C25: El modal debe mostrar el botón "Atrás" que regresa al modal de buscar usuario. | M25: x
... B43: 34 | C43: Mostrar/ocultar contraseña con ícono de ojo. | M43: x
B44: 35 | C44: Idioma seleccionable (ES/EN) en esquina superior. | N44: x
B45: 36 | C45: Validación de tiempo de sesión máxima configurable. | M45: x
B46: 37 | C46: Pantalla de términos y condiciones obligatoria en primer login. | M46: x
B47: 38 | C47: Pantalla de bienvenida personalizada tras login (con nombre). | M47: x
B48: 39 | C48: El sistema debe limpiar el historial de navegación para evitar que se pueda volver atrás tras cerrar sesión. | M48: x

Sheet Inicio de sesión NO FUN.
B2: SI | C2: Marque con una equis (X) si el sistema no cumple con la función descrita | V2: Volver
B3: NO | C3: Marque con una equis (X) si el sistema cumple con la función descrita
B4: ADI | C4: Marque con una equis (X) si el sistema debe adicionar la función descrita
B5: Observaciones: | D5: Espacio para complementar respuestas
B7: P
M8: Nivel de cumplimiento | P8: OBSERVACIONES
D9: REQUERIMIENTOS NO FUNCIONALES DEL INICIO DE SESIÓN | M9: SI | N9: NO | O9: ADI
B12: 1 | C12: Tiempo de respuesta < 2 segundos para validación de credenciales. | M12: x
B13: 2 | C13: Protección contra fuerza bruta con límite de intentos. | N13: x
B14: 3 | C14: Consistencia visual con paleta corporativa (verde, azul, blanco). | M14: x
B15: 4 | C15: Logs de auditoría de intentos de login (éxito/fracaso). | N15: x
B16: 5 | C16: Validación de entrada contra SQL Injection. | M16: x
B17: 6 | C17: Manejo de errores sin mostrar detalles técnicos al usuario. | M17: x
B18: 7 | C18: Carga inicial < 3 segundos en conexión de 10 Mbps. | M18: x
B19: 8 | C19: Compatibilidad con lectores de pantalla básica. | N19: x
B20: 9 | C20: Soporte para teclado (navegación completa sin mouse). | M20: x
B21: 10 | C21: Backend en PHP 7.4+ con buenas prácticas de codificación. | M21: x
B22: 11 | C22: Base de datos normalizada con índices para búsquedas de usuarios. | M22: x
B23: 12 | C23: Mensajes de error en español claro y amigable. | M23: x
B24: 13 | C24: No almacena contraseñas en texto plano ni logs. | M24: x
B25: 14 | C25: Doble validación del token de sesión (server-side + client-side). | N25: x
B26: 15 | C26: Los títulos y mensajes motivacionales deben cambiar de color suavemente al pasar el mouse. | M26: x
B27: 16 | C27: Uso de fuentes diferenciadas (Montserrat para títulos, Arial para cuerpo) para mejorar la lectura. | M27: x
B28: 17 | C28: Los bordes de los campos deben resaltar en azul y expandirse al ser seleccionados por el usuario. | M28: x
B29: 18 | C29: Los títulos (h1) deben cambiar de color suavemente al pasar el puntero sobre ellos. | M29: x
B30: 19 | C30: Separación total de la lógica de autenticación (JS) y los estilos visuales (CSS) en archivos externos. | M30: x
B31: 20 | C31: Los scripts de lógica deben cargarse al final del body para no retrasar la visualización del formulario. | M31: x

Sheet Registro FUN.
B2: SI | C2: Marque con una equis (X) si el sistema no cumple con la función descrita | V2: Volver
B3: NO | C3: Marque con una equis (X) si el sistema cumple con la función descrita
B4: ADI | C4: Marque con una equis (X) si el sistema debe adicionar la función descrita
B5: Observaciones: | D5: Espacio para complementar respuestas
B7: P
M8: Nivel de cumplimiento | P8: OBSERVACIONES
D9: REQUERIMIENTOS FUNCIONALES DE LA PÁGINA WEB | M9: SI | N9: NO | O9: ADI
B12: 1 | C12: Mostrar formulario de registro con campos: "Usuario", "Correo electrónico", "Contraseña", "Teléfono". | M12: x
B13: 2 | C13: Botón "REGISTRARSE" que envía datos al servidor. | M13: x
B14: 3 | C14: Mensaje de éxito "Registro completado" tras envío exitoso. | M14: x
B15: 4 | C15: Validación en tiempo real de campos obligatorios. | M15: x
B16: 5 | C16: Redirección automática a login tras registro exitoso. | M16: x
B17: 6 | C17: Sección "¡Hola, Amigo!" con mensaje motivacional junto enlace "INICIAR SESIÓN" visible y funcional. | M17: x
B18: 7 | C18: Validación de formato de correo electrónico (con @ y dominio). | M18: x
B19: 8 | C19: Verificación de que correo no esté ya registrado. | M19: x
B20: 9 | C20: Mínimo 8 caracteres para contraseña. | M20: x
B21: 10 | C21: Mensaje de error específico por campo (ej: "Correo ya registrado"). | M21: x
B22: 11 | C22: Campos marcados con asterisco (*) para indicar obligatoriedad. | M22: x
B23: 12 | C23: Logo corporativo visible en pantalla de registro. | N23: x
B24: 14 | C24: Campos con etiquetas claras en español. | M24: x
B25: 15 | C25: Validación contra inyección SQL en todos los campos. | M25: x
B26: 16 | C26: Bloqueo de envíos múltiples (prevenir doble clic en botón). | N26: x
B27: 17 | C27: Compatibilidad con navegación por teclado (Tab). | M27: x
B28: 18 | C28: Campo de contraseña con máscara de caracteres por defecto. | M28: x
B29: 19 | C29: Mostrar/ocultar contraseña con ícono de ojo en ambos campos. | M29: x
B30: 20 | C30: Indicador visual de fortaleza de contraseña (Falta una mayúscula, Falta un número, etc). | M30: x
B31: 21 | C31: Validación de fortaleza de contraseña (mínimo 1 mayúscula, 1 número). | M31: x
B32: 22 | C32: Checkbox "Acepto términos y condiciones" obligatorio. | M32: x
B33: 23 | C33: Enlace a términos y condiciones en nueva ventana. | M33: x
B34: 25 | C34: El campo de contraseña debe restringir el ingreso a menos de 8 caracteres. | M34: x
B35: 26 | C35: Al finalizar el registro el sistema debe mostrar un cuadro de texto que indique que el registro fue completado con éxito. | M35: x
B36: 27 | C36: El sistema debe eliminar espacios en blanco accidentales en usuario y correo antes de procesarlos (Trim). | M36: x
B37: 28 | C37: El sistema debe filtrar y eliminar cualquier carácter no numérico del campo teléfono. | M37: x
B38: 29 | C38: El sistema debe asegurar que si falla la asignación de permisos, el usuario no se cree (Rollback si algo sale mal). | M38: x
... B41: 32 | C41: Restringir el registro si el nombre de usuario tiene menos de 3 caracteres. | M41: x

Sheet Registro NO FUN.
B2: SI | C2: Marque con una equis (X) si el sistema no cumple con la función descrita | V2: Volver
B3: NO | C3: Marque con una equis (X) si el sistema cumple con la función descrita
B4: ADI | C4: Marque con una equis (X) si el sistema debe adicionar la función descrita
B5: Observaciones: | D5: Espacio para complementar respuestas
B7: P
M8: Nivel de cumplimiento | P8: OBSERVACIONES | S8: Diseño responsivo para móviles (probado en 320px+)
D9: REQUERIMIENTOS NO FUNCIONALES DE LA PÁGINA WEB | M9: SI | N9: NO | O9: ADI
B12: 1 | C12: Tiempo de respuesta < 3 segundos para procesar registro. | M12: x
B13: 2 | C13: Almacenamiento seguro de contraseñas con hash. | M13: x
B14: 3 | C14: Validación server-side además de client-side. | M14: x | R14: PHP valida longitud, formato de email y duplicados.
B15: 4 | C15: Contraste de colores adecuado para lectura. | M15: x
B16: 5 | C16: Mensajes de error en español claro y amigable. | M16: x
B17: 6 | C17: Logs de nuevos registros con fecha y hora. | M17: x
B18: 7 | C18: Protección contra spam con límite de registros por IP. | N18: x
B19: 8 | C19: Base de datos PostgreSQL con índices para búsqueda rápida | M19: x
B20: 9 | C20: Validación de entradas contra XSS y SQL injection. | M20: x | R20: Las sentencias preparadas del PHP lo cubren.
B21: 10 | C21: Cookies seguras para sesión post-registro. | M21: x
B22: 11 | C22: Backend PHP 7.4+ con prácticas básicas de seguridad. | M22: x | R22: Pruebas manuales realizadas en formulario de registro
B23: 13 | C23: Manejo de excepciones básico (no muestra errores técnicos). | M23: x
B24: 14 | C24: Consistencia visual con resto del sistema. | M24: x
B25: 15 | C25: Espaciado adecuado entre elementos del formulario. | M25: x
B26: 19 | C26: Sistema de alertas por registro sospechoso (muchos intentos). | N26: x
B27: 20 | C27: Soporte para nombres largos (hasta 50 caracteres sin truncar). | M27: x
B28: 21 | C28: Los títulos y mensajes motivacionales deben cambiar de color suavemente al pasar el mouse. | M28: x
B29: 22 | C29: Uso de fuentes diferenciadas (Montserrat para títulos, Arial para cuerpo) para mejorar la lectura. | M29: x
B30: 23 | C30: Bloquear la carga de la página de registro en marcos o iframes externos. | M30: x | R30: X-Frame-Options: DENY
B31: 24 | C31: No enviar información del sitio de origen al navegar a enlaces externos. | M31: x
B32: 25 | C32: Impedir que los datos sensibles del formulario se almacenen en el caché del navegador. | M32: x | R32: Cache-Control: no-store
B33: 26 | C33: El backend debe exigir tipos de datos exactos para minimizar errores de lógica. | M33: x
B34: 27 | C34: La lógica de acceso a la base de datos debe residir en un archivo independiente y protegido. | M34: x

Sheet Inf. Personal FUN.
B2: SI | C2: Marque con una equis (X) si el sistema no cumple con la función descrita | V2: Volver
B3: NO | C3: Marque con una equis (X) si el sistema cumple con la función descrita
B4: ADI | C4: Marque con una equis (X) si el sistema debe adicionar la función descrita
B5: Observaciones: | D5: Espacio para complementar respuestas
M8: Nivel de cumplimiento | P8: OBSERVACIONES
D9: REQUERIMIENTOS FUNCIONALES DE CLIENTE DE LA PÁGINA WEB | M9: SI | N9: NO | O9: ADI
B12: 1 | C12: Al iniciar como cliente, el sistema debe mostrar un header con: Logo Specialized, Nombre Specialized, Barra de búsqueda, Botón de carrito, Icono de usuario junto a su nombre, botón de salir. | M12: x
B13: 2 | C13: Tanto el logo como el nombre "Specialized" al momento de dar click deben redirigir al inicio del scroll de la página de cliente. | M13: x
B14: 3 | C14: La barra de búsqueda debe ser dinámica e ir mostrando resultados según lo que se escriba, si se borra el buscado, el sistema debe volver a mostrar todos los productos. | M14: x
B15: 4 | C15: EL botón de carrito debe desplegar un menú derecho (sidebar). | M15: x
B16: 5 | C16: El carrito, si no hay productos añadidos debe mostrar un botón "Ver Productos" que al dar click cierra el menú de carrito y vuelve a la vista principal de productos. | M16: x
B17: 6 | C17: Al añadir productos al carrito, el icono de este en la parte superior derecha debe mostrar un circulo rojo con el numero exacto que se añada al carrito. | M17: x
B18: 7 | C18: Al tener productos añadidos, en el menú (sidebar) de carrito, deben aparecer los productos con su nombre, precio, una opción para añadir o reducir cantidades y un botón con ícono de basura para eliminar el ítem. | M18: x
B19: 8 | C19: Si se reduce más de 1 cantidad, el producto desaparece del carrito. | M19: x
B20: 9 | C20: En la parte inferior del sidebar de carrito, el sistema debe calcular el total de productos añadidos al carrito. | M20: x
B21: 10 | C21: Al hacer click en el botón "Proceder al Pago ->" el sistema debe mostrar un modal con el mensaje "Funcionalidad de pago próximamente". | M21: x
B22: 11 | C22: Al dar click en el ícono de usuario, junto al nombre, el sistema debe desplegar un modal con el nombre "Modificar Perfil", con los campos: (Nombre de Usuario, Email, Télefono). | M22: x
B23: 12 | C23: El modal debe contener los datos del usuario actual en los campos correspondientes. | M23: x
... B34: 23 | C34: El botón "Aceptar" debe redirigir a la landing, el botón "Cancelar" debe mantener la sesión y cerrar el modal. | M34: x
B35: 24 | C35: Antes de la sección de productos debe haber un título y una descripción del sistema "SDI (Special Dental Instruments)". | N35: x | R35: el sistema es de admin
B36: 25 | C36: La sección de productos debe tener las siguientes etiquetas de filtro: "Todos, Estética, Esterilización, Endodoncia, Periodoncia, Kits". | M36: x
B37: 26 | C37: Los filtros deben ser funcionales, al dar click a algún filtro debe traer los productos de la categoría seleccionada. | M37: x
B38: 27 | C38: Los productos deben estar contenidos en tarjetas, con una etiqueta distintiva de su categoría, su imagen, su nombre, su descripción y su precio. | M38: x
B39: 28 | C39: Cada tarjeta debe tener un botón "+" que al dar click debe añadir el producto al carrito. | M39: x
B40: 29 | C40: La página debe tener un scroll funcional. | M40: x
B41: 30 | C41: Al expirar el tiempo del token, el sistema debe mostrar un modal con el título "Sesión Caducada", con el mensaje "Tu sesión se ha cerrado automáticamente por seguridad debido a inactividad o expiración del token." | M41: x
B42: 31 | C42: El modal de "sesión caducada" debe contener un botón "Aceptar y Salir" que al dar click en este, debe cerrar la sesión automáticamente y redirigir a la landing. | M42: x
B43: 32 | C43: El sistema no debe mostrar este icono si el usuario no ha iniciado sesión. | M43: x

Sheet Inf. Personal NO FUN.
B2: SI | C2: Marque con una equis (X) si el sistema no cumple con la función descrita | V2: Volver
B3: NO | C3: Marque con una equis (X) si el sistema cumple con la función descrita
B4: ADI | C4: Marque con una equis (X) si el sistema debe adicionar la función descrita
B5: Observaciones: | D5: Espacio para complementar respuestas
B7: P
M8: Nivel de cumplimiento | P8: OBSERVACIONES
D9: REQUERIMIENTOS FUNCIONALES DE LA PÁGINA WEB | M9: SI | N9: NO | O9: ADI
B12: 1
B13: 2
B14: 3
B15: 4
B16: 5
B17: 6
B18: 7
B19: 8
B20: 9

Sheet Panel Admin FUN.
B2: SI | C2: Marque con una equis (X) si el sistema no cumple con la función descrita | V2: Volver
B3: NO | C3: Marque con una equis (X) si el sistema cumple con la función descrita
B4: ADI | C4: Marque con una equis (X) si el sistema debe adicionar la función descrita
B5: Observaciones: | D5: Espacio para complementar respuestas
B7: P
M8: Nivel de cumplimiento | P8: OBSERVACIONES
C9: REQUERIMIENTOS FUNCIONALES DEL PANEL ADMINISTRADOR DE LA PÁGINA WEB | M9: SI | N9: NO | O9: ADI
B12: 1 | C12: Al entrar se carga un dashboard centralizado con métricas clave de la plataforma. | M12: x
B13: 2 | C13: Saludo dinámico y personalizado con el nombre del usuario en sesión. | M13: x
B14: 3 | C14: Tarjetas de métrica (Total Usuarios, Nuevos este mes, Empleados, Clientes, Proveedores, Productos en inventario, mayor venta, Menor producto en stock) conectadas a la base de datos. | M14: x
B15: 4 | C15: Interacción Dinámica de Métricas: Al accionar (click) cualquier tarjeta de estadísticas, el sistema debe inicializar y desplegar un modal de gestión contextualizado al módulo de la métrica seleccionada (Excepto en las tarjetas "Mayor venta" y "Menor producto en stock". | M15: x
B16: 5 | C16: La tarjeta "Productos en inventario" al hacer click sobre ella, el sistema debe redirigir al menú "Productos" para realizar la gestión correspondiente. | M16: x
B17: 6 | C17: Renderizado de Grillas de Datos: El cuerpo del modal debe visualizar una lista detallada con los campos técnicos correspondientes (ID, Nombre, Contacto, Estado, etc.) consultados en tiempo real desde la DB. | M17: x
B18: 7 | C18: Estandarización de Modales de Inserción: Al presionar "Nuevo" en cualquier modal de gestión, el sistema debe desplegar un formulario dinámico con los campos obligatorios correspondientes al módulo. | M18: x
B19: 8 | C19: El sistema debe restringir automáticamente la visibilidad del botón "Nuevo" en el modal de la tarjeta "Nuevos este mes", permitiendo únicamente funciones de consulta y desplegar una lista con los usuarios registrados en el mes actual con los campos (ID, Usuario, Email, Teléfono, Fecha Registro, Acciones). | M19: x
B20: 9 | C20: Gestión de Cierre y Navegación: El modal debe contar con un botón "Cerrar" en la parte inferior y una "X" en la esquina superior derecha que finalice la instancia del objeto modal y retorne el foco a la vista general del Panel de Administración. | M20: x
B21: 10 | C21: Validación Universal de Entradas: Todos los campos de entrada de datos en los modales deben contar con validaciones de tipo de dato, longitud mínima/máxima y obligatoriedad antes de ser enviados. | M21: x
B22: 11 | C22: Manejo de Errores desde la Base de Datos: El sistema debe capturar las excepciones lanzadas por PostgreSQL (ej. Violación de unicidad) y mostrar un mensaje claro al administrador sin interrumpir el flujo. | M22: x
B23: 12 | C23: Lógica de Borrado Lógico (Soft Delete): La eliminación de cualquier registro desde el panel administrativo debe realizarse mediante la actualización del campo ind_vivo a FALSE, manteniendo la integridad referencial. | M23: x
... B26: 15 | C26: Confirmación de Acciones Críticas: Antes de ejecutar un borrado o una actualización masiva, el sistema debe solicitar una confirmación visual al usuario para prevenir errores accidentales. | M26: x
B27: 16 | C27: Integración de Búsqueda en Listados: Todo modal que visualice una lista (Usuarios, Clientes, etc.) debe integrar un campo de filtrado por nombre o ID para localización rápida de registros. | N27: x
B28: 17 | C28: Reporte de Nuevos Registros: Filtrar y mostrar automáticamente los usuarios registrados cuya fecha de inserción corresponda al mes calendario actual. | M28: x
B29: 18 | C29: Gestión Centralizada de Empleados: Visualizar y gestionar datos técnicos del personal (Cargos, ID de documento, Estado contractual) mediante el modal de Empleados. | M29: x
B30: 19 | C30: Consolidado de Gestión de Clientes: Desplegar el listado de clientes profesionales y estudiantes con su respectiva información de contacto y ubicación. | M30: x
B31: 20 | C31: Visibilidad de Inventario General: La tarjeta de Gestión "Productos en inventario" debe consolidar la sumatoria de todos los instrumentos y kits que tengan el estado ind_vivo = TRUE. | M31: x
B32: 21 | C32: En el campo "Acciones" de las tarjetas deben haber dos botones funcionales para "Editar" y "Eliminar". | M32: x
B33: 22 | C33: Visualización de "Total Ventas" con montos acumulados de la DB en la esquina inferior derecha. | M33: x
B34: 23 | C34: Reporte rápido de "Ventas Diarias" en la sección de analítica en la esquina inferior derecha. | M34: x
B35: 24 | C35: El sistema debe mostrar un menú lateral izquierdo funcional con los accesos directos a "Instrumental", "Materia Prima", "Productos", "Finanzas","Historial". | M35: x
B36: 25 | C36: Botón "Instrumental" redirecciona a la gestión de productos y kits. | M36: x
B37: 26 | C37: Botón "Materia Prima" redirecciona a la gestión de la materia prima. | M37: x
B38: 27 | C38: Botón "Productos" redirecciona a la gestión de los productos comerciales. | M38: x
B39: 28 | C39: Botón "Finanzas" redirecciona a la gestión de las finanzas de la empresa. | M39: x
B40: 29 | C40: Botón "Historial" redirecciona a la gestión de historiales de la empresa. | M40: x
B41: 30 | C41: El sistema debe mostrar un menú lateral derecho (panel de configuración) que contenga de forma visible las opciones: "Modificar Perfil", "Cambiar Contraseña", "Configuración", "Exportar Datos", "Ayuda y Soporte" y "Cerrar Sesión". | M41: x | R41: agregar otras opciones detalladamente
B42: 31 | C42: Al accionar la opción "Modificar Perfil" desde el menú, el sistema debe desplegar un modal con los campos (Nombre de usuario, Email, Teléfono, Rol), permitiendo al administrador editar su información, guardar cambios con mensaje de éxito o cancelar la operación retornando al dashboard. | M42: x
B43: 32 | C43: Al accionar la opción "Cambiar Contraseña" desde el menú, el sistema debe desplegar un modal con los campos (Contraseña Actual, Nueva, Confirmación), validando la coincidencia de datos y confirmando el cambio exitoso mediante un mensaje emergente. | M43: x
B44: 33 | C44: Opción "Notificaciones", abre un modal que muestra de manera rápida si hay o no productos / materias primas que se encuentran en bajo stock. | M44: x
B45: 34 | C45: Opción "Configuración" accesible desde el panel. | M45: x
B46: 35 | C46: Opción "Ayuda y Soporte" abre un modal con los datós básicos de contacto de los desarrolladores del sistema. | M46: x
B47: 36 | C47: Al presionar "Cerrar Sesión", el sistema debe destruir la sesión actual del servidor y redirigir al Index de forma inmediata. | M47: x
B48: 37 | C48: Control de acceso por rol (Solo administradores ven este panel). | M48: x
B49: 38 | C49: Capacidad de colapsar los menus laterales para ganar área de trabajo. | N49: x
B50: 39 | C50: Carga asíncrona de estadísticas para no bloquear la interfaz. | M50: x
B51: 40 | C51: Botón de ayuda y soporte técnico directo para el administrador. | M51: x
B52: 41 | C52: El dashboard debe refrescar las cifras de las tarjetas cada vez que se detecte un cambio exitoso en la base de datos. | M52: x
B53: 42 | C53: Si un listado supera los 20 registros, el modal debe implementar una barra de desplazamiento (scroll) o paginación interna. | M53: x
B54: 43 | C54: Capacidad de visualizar registros marcados como inactivos y permitir su reactivación (cambio de ind_vivo). | N54: x | R54: funcional en los demas menus excepto en las tarjetas principales
B55: 44 | C55: Notificaciones de Éxito: Tras cada acción de "Guardar Cambios" o "Nuevo", mostrar un aviso flotante (Toast) confirmando la operación. | M55: x
B56: 45 | C56: Las listas en los modales deben mostrar una miniatura del producto o usuario si el registro cuenta con img_url. | N56: x
B57: 46 | C57: Los modales de inserción deben mostrar mensajes de ayuda indicando el formato correcto (ej: "Solo números" en teléfono). | M57: x
B58: 47
B59: 48
B60: 49
B61: 50
B62: 51
B63: 52
B64: 53
B65: 54
B66: 55
B67: 56
B68: 57
B69: 58
... B87: 76

Sheet Panel Admin NO FUN.
B2: SI | C2: Marque con una equis (X) si el sistema no cumple con la función descrita | V2: Volver
B3: NO | C3: Marque con una equis (X) si el sistema cumple con la función descrita
B4: ADI | C4: Marque con una equis (X) si el sistema debe adicionar la función descrita
B5: Observaciones: | D5: Espacio para complementar respuestas
B7: P
M8: Nivel de cumplimiento | P8: OBSERVACIONES
D9: REQUERIMIENTOS NO FUNCIONALES DEL PANEL ADMINISTRADOR | M9: SI | N9: NO | O9: ADI
B12: 1 | C12: El Dashboard debe reordenar las tarjetas en botones simples en la parte inferior al ser visto desde tablets. | M12: x
B13: 2 | C13: Efecto de elevación (floating effect) en tarjetas de métricas. | M13: x
B14: 3 | C14: Sombreado dinámico (box-shadow) al interactuar con elementos. | M14: x
B15: 4 | C15: Cambio de color suave en botones y opciones al pasar el mouse. | M15: x
B16: 5 | C16: Consistencia visual con paleta corporativa (Verde #087d4e / Azul #36498f). | M16: x
B17: 6 | C17: Transiciones fluidas de 0.3s en todos los efectos de hover. | M17: x
B18: 7 | C18: Diseño responsivo basado en Grid que se adapta a tablets. | M18: x
B19: 8 | C19: Sanitización de salida mediante htmlspecialchars() para prevenir XSS. | N19: x
B20: 9 | C20: Arquitectura modular con separación de Header, Sidebar y Footer. | M20: x
B21: 10 | C21: Cursor tipo 'pointer' habilitado en todas las tarjetas clicables. | M21: x
B22: 11 | C22: Iconografía estandarizada de FontAwesome para cada función. | M22: x
B23: 12 | C23: Tipografía profesional 'Montserrat' para títulos y 'Arial' para datos. | M23: x
B24: 13 | C24: Tiempo de carga inicial del dashboard inferior a 2 segundos. | M24: x
B25: 14 | C25: Contraste de color alto entre cifras numéricas y fondo de tarjetas. | M25: x
B26: 15 | C26: Código backend con tipado estricto (strict_types=1). | M26: x
B27: 16 | C27: Estilos CSS organizados en archivos externos independientes. | M27: x
B28: 17 | C28: Protección contra ataques de Clickjacking en el panel. | N28: x
B29: 18 | C29: Navegación intuitiva que no requiere curva de aprendizaje. | M29: x
B30: 19 | C30: Mensajes de error amigables sin exponer variables de sistema. | M30: x
B31: 20 | C31: Uso de variables CSS para consistencia de colores globales. | M31: x
B32: 21 | C32: Optimización de scripts JS al final del documento. | M32: x
B33: 22 | C33: Diseño de botones con bordes redondeados (15px) para estética moderna. | M33: x
B34: 23 | C34: Visualización limpia de tablas de datos sin saturación visual. | M34: x
B35: 24 | C35: El sistema debe resaltar el borde de las opciones del menú izquierdo en color blanco al detectar el evento hover. | M35: x
B36: 25 | C36: Las opciones del menú izquierdo deben incrementar su tamaño relativo respecto a los elementos adyacentes al pasar el mouse. | M36: x
B37: 26 | C37: El comportamiento de resaltado y escalado debe ser consistente tanto en el menú lateral izquierdo como en el derecho. | M37: x
B38: 27 | C38: La opción de menú seleccionada debe mantener un distintivo visual permanente mientras el administrador esté en ese módulo. | M38: x
B39: 28 | C39: El agrandamiento de los botones no debe desplazar o desordenar los elementos de contenido central del Dashboard. | M39: x
B40: 30 | C40: Todos los modales deben compartir el mismo estilo de bordes redondeados y tipografía. | M40: x
... B46: 36 | C46: Sincronización con el Controlador de Datos: Todas las tarjetas del dashboard deben consumir los datos procesados por el dashboard_controller.php. | M46: x
B47: 37
B48: 38
B49: 39
B50: 40
B51: 41
B52: 42
B53: 43
B54: 44
B55: 45
B56: 46
B57: 47
B58: 48

Sheet Instrumental FUN.
B2: SI | C2: Marque con una equis (X) si el sistema no cumple con la función descrita | T2: Volver
B3: NO | C3: Marque con una equis (X) si el sistema cumple con la función descrita
B4: ADI | C4: Marque con una equis (X) si el sistema debe adicionar la función descrita
B5: Observaciones: | D5: Espacio para complementar respuestas
B7: P
M8: Nivel de cumplimiento | P8: OBSERVACIONES
C9: REQUERIMIENTOS FUNCIONALES DE INSTRUMENTAL DENTRO DE LA PÁGINA WEB | M9: SI | N9: NO | O9: ADI
B12: 1 | C12: El sistema debe mostrar el botón "Volver al Inicio" que redirecciona al dashboard principal. | M12: x
B13: 2 | C13: El sistema debe mostrar la tarjeta "Instrumentos" y la tarjeta "Kits" junto con su breve descripción. | M13: x
B14: 3 | C14: Al dar click en la tarjeta "Instrumentos" el sistema debe abrir la gestión de instrumentos. | M14: x
B15: 4 | C15: Al entrar a una tarjeta, en la esquina superior izquierda debe estar el botón "Volver a Selección" que al interactuar con el, debe redirigir a la pestaña anterior con las tarjetas "Instrumentos" y "Kits". | M15: x
B16: 5 | C16: El sistema debe mostrar barras de búsqueda funcionales para facilitar la búsqueda en cada tarjeta. | M16: x
B17: 6 | C17: Las barras de búsqueda deben ser predictivas. | M17: x
B18: 7 | C18: El sistema debe limpiar los filtros de búsqueda automáticamente al navegar entre la gestión de Instrumentos y la gestión de Kits. | M18: x
B19: 8 | C19: Al extremo derecho de las barras de búsqueda debe estar el botón "Agregar Nuevo". | M19: x
B20: 9 | C20: Al dar click en la tarjeta "Agregar Nuevo" se debe abrir el modal "Nuevo registro" con los campos necesarios para agregar un nuevo instrumental o kit (Nombre Instrumento/kit, Cantidad, Lote,etc). | M20: x | R20: agregar campo para img
B21: 10 | C21: El modal de "Nuevo Registro" debe contar con los botones "Cancelar" que regresa al listado de instrumentos/kits y "Guardar" que registra los cambios realizados. | M21: x
B22: 11 | C22: En instrumentos, el sistema debe desplegar un listado con vistas en tarjeta de todos los instrumentos, con su cantidad disponible, vista previa de la imagen, nombre, especialización a la que pertenece, referencia (id), y botones para actualizar y eliminar. | M22: x | R22: quitar id
B23: 12 | C23: Al dar click en cualquier tarjeta de cualquier instrumento, el sistema debe abrir una vista detallada del instrumento (Mostrando su imagen, nombre, especializacion, referencia, cantidad actual, stock min/max, material, lote y su registro invima). | M23: x
B24: 13 | C24: Los modales de detalles de instrumentos deben tener su botón "x" o "Cerrar" en la parte inferior para cerrar los detalles de un instrumento. | M24: x
B25: 14 | C25: Al dar click en el botón "Editar" dentro del modal de detalles de un instrumento, el sistema debe abrir un nuevo modal llamado "Editar Instrumento" con los campos: Especialización, Nombre Instrumento, Cantidad Disponible, Lote, Registro INVIMA, Numeral en kit (Si aplica), Tipo de material, Imagen, Stock min/max), junto con los botones "Cancelar" y "Guardar". | M25: x
B26: 15 | C26: Desde la vista de tarjetas, al interactuar con el botón "Lápiz" también debe abrir el modal "Editar Instrumento". | M26: x
B27: 16 | C27: El modal "Editar Instrumento" debe traer información actual del instrumento, campos rellenados con los datos actuales del instrumento. | M27: x
B28: 17 | C28: Tras actualización exitosa, el sistema debe mostrar un modal con el título "¡Éxito!", una descripción y el botón "Aceptar" que cierra todos los modales al interactuar con él. | M28: x
B29: 18 | C29: El sistema no debe dejar guardar, ni crear un instrumento nuevo si hay campos en rojo, en dado caso que pase estas validaciones, debe mostrar un modal con el título "Datos inválidos" con un mensaje descriptivo y amigable para el usuario, junto con el botón "Cerrar", para volver a la edición o creación de un instrumento. | M29: x
B30: 19 | C30: El botón "Basura" en la vista tarjetas de instrumentos, al interactuar con el, debe mostrar un mensaje de confirmación al usuario antes de borrar un registro, al elegir la opción "Sí, eliminarlo", el sistema debe pasar el "ind_vivo" de ese instrumento a "FALSE". Si elige la opción "Cerrar", el modal de confirmación se debe cerrar dejando la vista de instrumentos. | M30: x
B31: 20 | C31: Al dar click en la tarjeta "Kits" el sistema debe abrir la gestión de kits. | M31: x
B32: 21 | C32: En Kits, el sistema debe desplegar un listado con vistas en tarjeta de todos los Kits, con su cantidad disponible, vista previa de la imagen, nombre, especialización a la que pertenece, referencia (id), y botones para actualizar y eliminar. | M32: x
B33: 22 | C33: Al dar click en cualquier tarjeta de cualquier kit, el sistema debe abrir una vista detallada del kit (Mostrando su imagen, nombre, especializacion, referencia, cantidad actual, stock min/max y el contenido del kit (instrumentos que tiene). | M33: x
B34: 23 | C34: Los modales de detalles de kits deben tener su botón "x" o "Cerrar" en la parte inferior para cerrar los detalles de un kit. | M34: x
... B52: 41 | C52: El catálogo de la Landing Page debe ser de "Solo lectura" (Modo vitrina), sin carrito de compras ni pasarela de pagos. | M52: x
B53: 42 | C53: Al hacer clic en un producto en la Landing Page, se debe mostrar su detalle, foto y un botón de "Contactar Asesor" (WhatsApp). | N53: x
B54: 43 | C54: El sistema administrativo debe permitir subir una foto referencial para cada "Producto Comercial". | M54: x | R54: Mejor que use la imagen ya asignada a instrumento o kits
B55: 44 | C55: Si el stock físico de un Instrumento o Kit llega a cero, el "Producto Comercial" asociado debe mostrarse automáticamente como "Agotado" en la Landing Page (o ocultarse, según preferencia). | N55: x
B56: 45 | C56: El Administrador debe poder editar el "Nombre Comercial" y "Descripción" del producto para la web, que puede ser diferente al nombre técnico del inventario. | M56: x
C59: REQUERIMIENTOS FUNCIONALES DE INSTRUMENTAL DENTRO DE LA BASE DE DATOS
B62: 1 | C62: El sistema debe permitir gestionar productos terminados clasificándolos como "Instrumentos" o "Kits". | M62: x
B63: 2 | C63: La función de gestión de productos debe impedir que un producto sea Instrumento y Kit simultáneamente. | M63: x
B64: 3 | C64: El sistema debe validar que el nombre del producto comercial no esté vacío. | M64: x
B65: 4 | C65: Al crear un producto, el sistema debe verificar que la referencia de inventario (ID Instrumento o ID Kit) exista y esté activa. | M65: x | R65: revisar
B66: 5 | C66: El sistema debe permitir actualizar el precio de venta público de los productos del catálogo. | M66: x
B67: 6 | C67: El sistema debe permitir la eliminación lógica de productos del catálogo para que no aparezcan en ventas. | M67: x
B68: 7 | C68: La base de datos debe permitir asociar una imagen (URL) a cada ítem del catálogo. | M68: x
B69: 8 | C69: El sistema debe validar que el precio del producto sea mayor o igual a cero. | M69: x
B70: 9 | C70: La consulta de catálogo debe permitir filtrar por tipo de producto (Instrumento/Kit). | M70: x
B71: 10 | C71: El sistema debe mostrar la disponibilidad (Stock) real calculada desde las tablas de inventario. | M71: x
B72: 11
B73: 12
B74: 13

Sheet Instrumental NO FUN.
B2: SI | C2: Marque con una equis (X) si el sistema no cumple con la función descrita | T2: Volver
B3: NO | C3: Marque con una equis (X) si el sistema cumple con la función descrita
B4: ADI | C4: Marque con una equis (X) si el sistema debe adicionar la función descrita
B5: Observaciones: | D5: Espacio para complementar respuestas
B7: P
M8: Nivel de cumplimiento | P8: OBSERVACIONES
C9: REQUERIMIENTOS NO FUNCIONALES DE INSTRUMENTAL DENTRO DE LA PÁGINA WEB | M9: SI | N9: NO | O9: ADI
B12: 1 | C12: (UI / UX) La vista de selección debe utilizar tarjetas con el color institucional azul para "Instrumentos" y verde para "Kits". | M12: x
B13: 2 | C13: Las imágenes de las tarjetas de selección deben tener un tamaño de 100x100px y estar dentro de un contenedor circular blanco. | M13: x
B14: 3 | C14: El título de la tarjeta de selección debe utilizar mayúsculas sostenidas y un peso de fuente de 800 (Extra Bold). | M14: x
B15: 4 | C15: El hover de las tarjetas de selección debe aplicar un transform: scale(1.02) y una sombra azulada de rgba(54, 73, 143, 0.2). | M15: x
B16: 5 | C16: Las tarjetas de kits individuales deben mostrar un badge de disponibilidad en la esquina superior derecha con fondo blanco opaco (0.9). | M16: x
B17: 6 | C17: El encabezado de la gestión de instrumentos debe tener un padding de 20px y una animación de entrada 'fadeIn' de 0.3s. | M17: x
B18: 7 | C18: Los botones de acción en las tarjetas (Lápiz, Basura) deben tener una opacidad de 1 y ser siempre visibles. | M18: x
B19: 8 | C19: La tabla de datos debe tener encabezados pegajosos (sticky) con un z-index de 10 para facilitar el scroll. | M19: x
B20: 9 | C20: El color de la fila de encabezado en la tabla de instrumental debe coincidir con el color de la tarjeta de selección (#36498f). | M20: x
B21: 10 | C21: Los modales detallados deben cargar la imagen del instrumento con un tamaño máximo de 250px de altura. | M21: x
B22: 11 | C22: El scroll de la vista de kits debe ser vertical y suave, aplicado al contenedor principal .a2. | M22: x
B23: 12 | C23: Las insignias de "Bajo Stock" en las tarjetas de instrumental deben ser de color rojo #dc3545. | M23: x | R23: revisar
B24: 13 | C24: (USABILIDAD) La barra de búsqueda de instrumentos debe tener un ícono de lupa posicionado a 15px a la izquierda del input. | M24: x
B25: 14 | C25: El sistema debe filtrar los resultados automáticamente al ingresar texto, sin presionar "Enter". | M25: x
B26: 15 | C26: Los procesos de edición deben cargar datos previos en los campos del formulario automáticamente. | M26: x
B27: 16 | C27: El campo "Cantidad Disponible" en instrumental debe resaltarse visualmente si el valor es 0. | M27: x
C28: Los kits deben validar un contenido mínimo de 3 instrumentos y un máximo de 10 instrumentos vinculados. | M28: x
C29: El botón "Agregar Instrumento" en el modal de kits debe añadir dinámicamente campos de selección al formulario. | M29: x
B31: 18 | C31: Al entrar a la sección "Instrumental" los demás menus deben inhabilitarse de tal forma que no se pueda acceder a ellos por el menú lateral izquierdo. | M31: x
B32: 19 | C32: El botón del módulo activo ("Instrumental") debe incrementar su luminosidad y escala para diferenciarse de los módulos inactivos. | M32: x
B33: 20 | C33: Los elementos de navegación no permitidos deben presentar una opacidad reducida (0.5 o menor) como indicador de deshabilitación. | M33: x
B34: 21 | C34: Las opciones de menú deben mostrar un borde blanco definido y agrandar su tamaño relativo al detectar el cursor. | M34: x
B35: 22 | C35: Implementación de translateY negativo y aumento de box-shadow al pasar el mouse sobre las tarjetas de instrumentos o kits. | M35: x
B36: 23 | C36: Aparición de una barra azul en la parte inferior de la tarjeta "Instrumentos" al activarse el evento hover. | M36: x
B37: 24 | C37: Aparición de una barra verde en la parte inferior de la tarjeta "Kits" al activarse el evento hover. | M37: x
B38: 25 | C38: Todas las animaciones de escala y color deben tener una transición de 0.3s con curva ease. | M38: x
B39: 26 | C39: Uso prioritario de la fuente 'Segoe UI' o 'Montserrat' para garantizar la legibilidad de las descripciones técnicas. | M39: x
B40: 27 | C40: Uso unificado de border-radius (entre 10px y 25px) en todos los componentes interactivos para una estética moderna. | M40: x
B41: 28 | C41: Separación total de la hoja de estilos (estilos_menuPrincipal.css) de la estructura HTML y la lógica PHP. | M41: x
B42: 29 | C42: Uso de htmlspecialchars para prevenir ataques XSS al mostrar nombres de instrumentos. | N42: x | R42: ??
B43: 30 | C43: Integración de FontAwesome mediante CDN para asegurar que los glifos no retrasen el renderizado visual. | M43: x
B44: 31 | C44: Los mensajes de alerta o validación deben presentarse en modales con diseño coherente al resto del sistema. | M44: x
B45: 32 | C45: Animación de brillo o cambio de fondo en el botón "Volver al Inicio" para incitar a la acción. | M45: x
B46: 33
B47: 34 | C47: Modal "Editar instrumento", debe traer de la base de datos, información correspondiente para llenar los campos (Especialización). | M47: x
B48: 35 | C48: Modal "Editar Kit", debe traer de la base de datos, información correspondiente para llenar los campos (Especialización, Buscar instrumento…). | M48: x
B49: 36
B50: 37
B51: 38
C54: REQUERIMIENTOS NO FUNCIONALES DE INSTRUMENTAL DENTRO DE LA BASE DE DATOS
B57: 2 | C57: Las imágenes del catálogo deben referenciarse por ruta (URL) y no almacenarse como BLOB en la base de datos para no afectar el rendimiento. | M57: x
B58: 3 | C58: La búsqueda de productos por nombre debe ser insensible a mayúsculas/minúsculas y acentos. | M58: x
B59: 5 | C59: La estructura debe permitir agregar nuevas categorías de productos en el futuro sin modificar la lógica principal. | M59: x
B60: 6
B61: 7
B62: 8
B63: 9
B64: 10
B65: 11
B66: 12
B67: 13

Sheet Materia prima FUN.
B2: SI | C2: Marque con una equis (X) si el sistema no cumple con la función descrita | V2: Volver
B3: NO | C3: Marque con una equis (X) si el sistema cumple con la función descrita
B4: ADI | C4: Marque con una equis (X) si el sistema debe adicionar la función descrita
B5: Observaciones: | D5: Espacio para complementar respuestas
B7: P
M8: Nivel de cumplimiento | P8: OBSERVACIONES
C9: REQUERIMIENTOS FUNCIONALES DE MATERIA PRIMA DENTRO DE LA PÁGINA WEB | M9: SI | N9: NO | O9: ADI
B12: 1 | C12: El sistema debe mostrar el botón "<- Volver al Inicio" que redirecciona al dashboard principal. | M12: x
B13: 2 | C13: Título "Materia Prima" visible. | M13: x
B14: 3 | C14: Botón "Registrar Movimiento" funcional, al dar click en este, el sistema debe abrir un modal con el título "Registrar Movimiento". | M14: x
B15: 4 | C15: Dentro del modal "Registrar Movimiento", el sistema debe mostrar los campos: Proveedor, Materia Prima, Tipo Movimiento, Cantidad Unidades, Observaciones. Con los botones "Cancelar" y "Registrar". | M15: x
B16: 5 | C16: El sistema debe obligar al usuario a seleccionar un proveedor para mostrar las materias primas correspondientes. Al seleccionar un proveedor, el sistema debe habilitar el campo "Materia Prima". Al hacer click sobre estos campos el sistema debe desplegar una listado. | M16: x
B17: 6 | C17: El campo "Tipo Movimiento" debe desplegar un listado al hacer click sobre este, con las siguientes opciones: "1. Entrada (Compra)", "2. Salida (Producción)", "3. Ajuste (Entrada +)" y "4. Daño (Salida -)". | M17: x
B18: 7 | C18: Botón "Cancelar" cierra el modal de "Registrar Movimiento". | M18: x
C19: Al llenar todos los campos de forma correcta y dar click en el botón "Registrar", el sistema debe mostrar un modal con el texto "¿Confirmar registro de movimiento? Esta acción afectará el inventario.", si el usuario da click en "Cancelar" este modal se cierra. | M19: x
C20: Si el usuario da click en "Aceptar", el botón "Registrar" debe pasar a "Guardando…", si todo salió bien, el sistema debe abrir un nuevo modal con el texto "Movimiento registrado con éxito.", tras dar click en el botón "Aceptar" el sistema debe cerrar todos los modales, y los cambios se deben haber realizado. | M20: x
B21: 8 | C21: Si el usuario da click en "Aceptar", el botón "Registrar" debe pasar a "Guardando…", si algo salio mal, el sistema debe abrir un nuevo modal con el texto "Error:" y un mensaje específico y amigable, tras dar click en el botón "Aceptar" el sistema debe dejar en la vista el panel "Registrar Movimiento" visible nuevamente. | M21: x
B22: 9 | C22: El sistema debe mostrar una vista en tarjetas de las categorías disponibles junto a su nombre. | M22: x
B23: 10 | C23: Al dar click en una tarjeta, el sistema debe abrir un nuevo menú para gestionar las materias primas de la categoría seleccionada. | M23: x
B24: 11 | C24: El sistema debe mostrar el botón "<- Volver a categorías" que redirige a la vista anterior de categorías. | M24: x
B25: 12 | C25: El sistema debe mostrar el título "Materias Primas: (Categoría Seleccionada)". | M25: x
B26: 13 | C26: El sistema debe mostrar el botón " + Agregar Nueva Materia" que al dar click en este, el sistema debe abrir un nuevo modal-formulario con los siguientes campos: Nombre Materia Prima, Stock Mínimo / Máximo, Imagen, Proveedor, Valor de Medida, Unidad de medida Lote Inicial, Tipo Material, Cantidad Inicial. | M26: x
B27: 14 | C27: Los campos "Proveedor" y "Unidad de Medida" deben desplegar listas de opciones al dar click en estas. | M27: x
B28: 15 | C28: Al dar click en el botón "Guardar" y todos los campos sean válidos, el sistema debe abrir un modal con el título "¡Éxito!" con el mensaje "Registro guardado correctamente" y el botón "Aceptar", que al dar click en este, cierra todos los modales y dejar visible la gestión de la categoría seleccioanda anteriormente. | M28: x
B29: 16 | C29: Al dar click en el botón "Guardar" y algún campo sea inválido, el sistema debe abrir un modal con el título "Datos inválidos" con el mensaje "Por favor corrija los campos marcados en rojo." y el botón "Cerrar", que al dar click en este, cierra el modal de error y deja visible el modal de creación de la materia prima. | M29: x
B30: 17 | C30: El sistema debe desplegar una vista en tarjetas de las materias primas existentes según la categoría, con su respectiva imagen, nombre, id de referencia, cantidad disponible, stock mínimo y los botones "Editar", "Detalle" y "Eliminar". | M30: x
B31: 18 | C31: Al dar click en el botón "Editar" el sistema debe abrir el modal "Editar Materia Prima", el modal debe tener los siguientes campos: Nombre Materia Prima, Stock Mín/Máx, Imagen, Proveedor, Valor de medida, Unidad de medida. | M31: x
B32: 19 | C32: Los campos deben tener los datos actuales de la materia prima seleccionada. | M32: x
... B43: 30 | C43: Al dar click sobre el botón "Eliminar", el sistema debe eliminar de la vista la categoría seleccionada, si no depende de registros, si depende de registros el sistema no debe dejar borrar la categoría. | M43: x
B44: 31
B45: 32
B46: 33
B47: 34
B48: 35
B49: 36
B50: 37
B51: 38
B52: 39
B53: 40
B54: 41
C57: REQUERIMIENTOS FUNCIONALES DE MATERIA PRIMA DENTRO DE LA BASE DE DATOS
B60: 1 | C60: El sistema debe permitir registrar movimientos de entrada (Compras) y salida (Producción) en el Kardex de Materia Prima. | M60: x
B61: 2 | C61: La función de Kardex debe validar que la cantidad del movimiento sea siempre mayor a cero. | M61: x
B62: 3 | C62: El sistema debe impedir registrar movimientos si la materia prima o el proveedor están inactivos. | N62: x | R62: revisar
B63: 4 | C63: Al registrar una salida (Tipos 2 o 4), el sistema debe validar que exista stock suficiente en la bodega del proveedor específico. | M63: x
B64: 5 | C64: La función debe actualizar el stock físico en la tabla tab_mat_primas_prov inmediatamente después de registrar el Kardex. | M64: x
B65: 6 | C65: El sistema debe concatenar el nombre del proveedor en la observación del Kardex para mantener la trazabilidad. | M65: x
B66: 7 | C66: El sistema debe validar que exista una relación comercial previa entre el proveedor y la materia prima antes de mover inventario. | M66: x
B67: 8 | C67: La función debe soportar tipos de movimiento definidos: 1-Compra, 2-Producción, 3-Ajuste, 4-Daño. | M67: x
B68: 9 | C68: El sistema debe lanzar una alerta o excepción si se intenta extraer más cantidad de la disponible (Stock negativo no permitido en MP). | M68: x
B69: 10 | C69: La inserción en el Kardex debe generar un ID autoincremental único por movimiento. | M69: x
B70: 11
B71: 12
B72: 13

Sheet Materia prima NO FUN.
B2: SI | C2: Marque con una equis (X) si el sistema no cumple con la función descrita | V2: Volver
B3: NO | C3: Marque con una equis (X) si el sistema cumple con la función descrita
B4: ADI | C4: Marque con una equis (X) si el sistema debe adicionar la función descrita
B5: Observaciones: | D5: Espacio para complementar respuestas
B7: P
M8: Nivel de cumplimiento | P8: OBSERVACIONES
C9: REQUERIMIENTOS NO FUNCIONALES DE MATERIA PRIMA DENTRO DE LA PÁGINA WEB | M9: SI | N9: NO | O9: ADI
B12: 1 | C12: (UI, UX) Los títulos de sección deben utilizar la fuente 'Segoe UI' con un tamaño de 1.4rem y color #36498f. | M12: x
C13: Los botones de acción principal (Registrar) deben tener el color institucional verde #087d4e. | M13: x
C14: El botón flotante de "Administrar Categorías" debe tener un índice de elevación z-index de 900. | M14: x
C15: Las tarjetas de categorías deben tener un redondeo de bordes (border-radius) de 15px. | M15: x
C16: El contenedor "materia-prima-root" debe tener un padding superior de 100px para evitar solapamiento con el header. | M16: x
C17: La animación de entrada de las vistas debe ser 'fadeIn' con una duración de 0.4s y curva 'ease-out'. | M17: x
C18: En el listado de categorías, el gap entre tarjetas debe ser de exactamente 25px. | M18: x
B19: 5 | C19: El sistema se debe adaptar a las categorías, debe desplegar un scroll si existen más de 12 categorías. | M19: x
B20: 6 | C20: Modal "Registrar Movimiento", debe traer de la base de datos, información correspondiente para llenar los campos (Proveedor, Materia Prima, Unidad de Medida). | M20: x
C23: REQUERIMIENTOS NO FUNCIONALES DE MATERIA PRIMA DENTRO DE LA BASE DE DATOS
B26: 1 | C26: El registro de un movimiento en el Kardex debe ser atómico para evitar inconsistencias de inventario. | N26: x | R26: revisar
B27: 2 | C27: El sistema debe ser capaz de manejar lotes de materia prima con precisión decimal (para medidas como gramos o metros). | M27: x
B28: 3 | C28: La consulta de stock actual de materia prima debe ser instantánea (tiempo real). | M28: x
B29: 4 | C29: El sistema debe mantener la integridad histórica del Kardex; los registros no deben poder ser modificados ni borrados. | M29: x
B30: 5 | C30: Las validaciones de stock deben ejecutarse antes de cualquier escritura en disco para optimizar recursos. | M30: x
B31: 6
B32: 7
B33: 8
B34: 9
B35: 10
B36: 11
B37: 12
B38: 13

Sheet Productos FUN
B2: SI | C2: Marque con una equis (X) si el sistema no cumple con la función descrita | V2: Volver
B3: NO | C3: Marque con una equis (X) si el sistema cumple con la función descrita
B4: ADI | C4: Marque con una equis (X) si el sistema debe adicionar la función descrita
B5: Observaciones: | D5: Espacio para complementar respuestas
B7: P
M8: Nivel de cumplimiento | P8: OBSERVACIONES
C9: REQUERIMIENTOS FUNCIONALES DE LA GESTIÓN DE PRODUCTOS DENTRO DE LA PÁGINA WEB | M9: SI | N9: NO | O9: ADI
B12: 1 | C12: El sistema muestra una barra de búsqueda funcional, junto con filtros para buscar productos "Habilitados" o "Inhabilitados" y para filtrar por si son "Instrumentos" o "Kits". | M12: x
B13: 2 | C13: En la parte derecha de la barra de búsqueda el sistema muestra el botón "Agregar Nuevo". | M13: x
B14: 3 | C14: "Agregar Nuevo" tiene los campos "Nombre del Producto", "Precio de venta", "Imagen del Producto", "Tipo de item" y el campo "Buscar Instrumento/Kit" según la selección del "Tipo de item". Junto con los botones "Cancelar" y "Guardar". | M14: x
B15: 4 | C15: Al envíar el form, el sistema muestra un Sweet Alert "Cargando" verificando los datos, si todo sale bien el sistema muestra un Sweet Alert de éxito, si algo sale mal el sistema muestra un Sweet Alert de error con el mensaje específico. | M15: x
B16: 5 | C16: El sistema desplega una vista de tarjetas de los productos comerciales creados, las tarjetas contienen, campo para imagen, su precio, su nombre, su tipo (Instrumento / Kit), su referente específico, el lápiz para editar y la basura para inhabilitar el registro. | M16: x
B17: 6 | C17: El sistema filtra según la selección del usuario, por defecto carga los productos "Habilitados", al darle click al botón "Inhabilitados" el sistema procede a cargar los productos inhabilitados. | M17: x
B18: 7 | C18: Si el usuario desea inhabilitar un producto, el sistema muestra un Sweet Alert de confirmación, tras confirmar la inhabilitación, el sistema muestra un Sweet Alert de éxito. | M18: x
B19: 8 | C19: Al inhabilitar un producto, este pasará al menú de inhabilitados y se dejará de mostrar en la landing como producto comercial. | M19: x
B20: 9 | C20: Al dar click sobre el botón del "Lápiz" el sistema muestra el modal de edición con los campos "Nombre del producto", "Precio de venta", "Imagen del Producto", "Tipo de item" y "Buscar Instrumento / kit". | M20: x
B21: 10 | C21: Tras actualización exitosa, el sistema muestra primero un Sweet Alert "Cargando", para si todo salió bien, el sistema mostrará un Sweet Alert de éxito. De lo contrario el sistema mostrará un Sweet Alert rojo indicando el error | M21: x
B22: 11 | C22: Los productos inhabilitados tienen el ícono de la basurita, pero en color verde y una flecha hacia arriba, indicando que puedes restaurar el registro. | M22: x
B23: 12 | C23: Si el usuario desea restaurar un producto, el sistema muestra un Sweet Alert de confirmación, tras confirmar el sistema muestra un nuevo Sweet Alert de éxito. | M23: x
B24: 13 | C24: Scroll funcional en el menú de productos. | M24: x
B25: 14
B26: 15
B27: 16
B28: 17
B29: 18
B30: 19
B31: 20
C34: REQUERIMIENTOS FUNCIONALES DEL HISTORIAL DENTRO DE LA BASE DE DATOS
B37: 1
B38: 2
B39: 3
B40: 4
B41: 5
B42: 6
B43: 7
B44: 8
B45: 9
B46: 10
B47: 11
B48: 12

Sheet Productos NO FUN
B2: SI | C2: Marque con una equis (X) si el sistema no cumple con la función descrita | V2: Volver
B3: NO | C3: Marque con una equis (X) si el sistema cumple con la función descrita
B4: ADI | C4: Marque con una equis (X) si el sistema debe adicionar la función descrita
B5: Observaciones: | D5: Espacio para complementar respuestas
B7: P
M8: Nivel de cumplimiento | P8: OBSERVACIONES
C9: REQUERIMIENTOS NO FUNCIONALES DE LA GESTIÓN DE PRODUCTOS DENTRO DE LA PÁGINA WEB | M9: SI | N9: NO | O9: ADI
B12: 1 | C12: (Estética y Diseño Visual (UI/UX)) El área de trabajo debe usar un fondo gris muy claro o blanco hueso (#f4f6f9) para dar sensación de limpieza y amplitud. | M12: x
B13: 2 | C13: El título "Inventario de Productos" debe usar una fuente en color azul marino oscuro (#1e3a8a o similar). | M13: x
B14: 3 | C14: Todo el bloque de herramientas y tarjetas debe estar contenido en un gran panel blanco con bordes redondeados (15px) y una sombra sutil. | M14: x
B15: 4 | C15: El buscador debe tener un fondo gris claro suave (#f1f5f9), sin bordes fuertes, y un radio de esquina de 50px. | M15: x
B16: 5 | C16: El nombre del producto debe ir en color negro o gris oscuro (#1e293b) con peso 700 para máxima legibilidad. | M16: x
B17: 6 | C17: Botones, Filtros y Píldoras (Interacciones) Botón Agregar Nuevo: Debe resaltar en color azul marino oscuro con texto blanco, ubicado estratégicamente a la derecha del buscador. | M17: x
B18: 7 | C18: Habilitados (ACTIVO) - Fondo: Azul marino sólido. Texto e Icono: Blanco. Icono: fa-circle-check (Check). | M18: x
B19: 8 | C19: Habilitados (INACTIVO) - Fondo: Blanco puro. Borde: Azul marino (1px solid). Texto e Icono: Azul marino. Icono: fa-circle-check sin rellenar. | M19: x
B20: 9 | C20: Inhabilitados (ACTIVO) - Fondo: Rojo sólido (#ef4444). Texto e Icono: Blanco. Icono: fa-circle-xmark o similar. | M20: x
B21: 10 | C21: Inhabilitados (INACTIVO) - Fondo: Blanco puro. Borde: Rojo (1px solid #ef4444). Texto e Icono: Rojo. Icono: fa-circle-xmark sin rellenar. | M21: x
B22: 11 | C22: Instrumentos (ACTIVO) - Fondo: Azul/Púrpura claro sólido, Borde: Azul/Púrpura claro sólido, Texto e Icono: Blanco puro (#ffffff). Acción: Se activa el texto flotante "Filtrando por: Instrumentos [x]". | M22: x
B23: 12 | C23: Instrumentos (INACTIVO) - Fondo: Blanco puro (#ffffff), Borde: Azul/Púrpura claro (1px solid #3b82f6), Texto e Icono: Azul/Púrpura claro. Icono: Icono de instrumental dental (fa-tooth o similar). | M23: x
... B38: 27 | C38: Alternar entre "Instrumentos" y "Kits" debe actualizar la cuadrícula en un tiempo menor a 200ms. | M38: x
B39: 28
B40: 29
C43: REQUERIMIENTOS FUNCIONALES DEL HISTORIAL DENTRO DE LA BASE DE DATOS
B46: 1
B47: 2
B48: 3
B49: 4
B50: 5
B51: 6
B52: 7
B53: 8
B54: 9
B55: 10
B56: 11
B57: 12

Sheet Finanzas FUN
B2: SI | C2: Marque con una equis (X) si el sistema no cumple con la función descrita | V2: Volver
B3: NO | C3: Marque con una equis (X) si el sistema cumple con la función descrita
B4: ADI | C4: Marque con una equis (X) si el sistema debe adicionar la función descrita
B5: Observaciones: | D5: Espacio para complementar respuestas
B7: P
M8: Nivel de cumplimiento | P8: OBSERVACIONES
C9: REQUERIMIENTOS FUNCIONALES DE LA GESTIÓN DE FINANZAS DENTRO DE LA PÁGINA WEB | M9: SI | N9: NO | O9: ADI
B12: 1 | C12: Al entrar al menú "Finanzas" el botón de este menú debe resaltar ligeramente sobre los otros. | M12: x
B13: 2 | C13: El sistema muestra un título y subtitulo resumiendo la funcionalidad del menú. | M13: x
B14: 3 | C14: En la parte superior de la derecha el sistema tiene un sistema de filtros funcionales por fecha mensual y anual. | M14: x
B15: 4 | C15: En la parte superior derecha el sistema tiene el botón "Exportar Excel", que descarga un excel con la siguiente información: "ID Factura, Fecha, Mes, Productos, Comprados, Cliente, Total, Medio de Pago.", según la fecha seleccionada. | M15: x
B16: 5 | C16: En caso de que no haya registros en la fecha seleccionada, el sistema muestra una sweet alert con el texto "Atención, No hay datos detallados para el periodo seleccionado.", y no descarga ningún excel. | M16: x
B17: 6 | C17: El sistema carga las tarjetas "Ingresos Mensuales", "Utilidad Neta del Mes", "Tasa de Retorno", "Alertas de Reabastecimiento". | M17: x
B18: 7 | C18: Debajo de las tarjetas principiales, el sistema mostrara el "Ticket Promedio Por Especialidad" en la parte izquierda de la página, el sistema calcula automáticamente el valor promedio de las transacciones agrupadas por especialidad odontológica (Endodoncia, Periodoncia, etc.) en un periodo de tiempo determinado. | M18: x
B19: 8 | C19: En la parte derecha, el sistema mostrara un pastel que se llena automáticamente con los medios de pago seleccionados, en el momento de registrar una venta. | M19: x
B20: 9 | C20: En la parte inferior de la sección de finanzas, el sistema muestra las "Previsiones de Compra (Stock Crítico)", que, al momento que la cantidad de una materia prima esté igual o menor al stock crítico, se mostrará en esta sección inferior con la posibilidad de mandar un mensaje de whatsapp al proveedor específico. | M20: x
B21: 10
B22: 11
B23: 12
B24: 13
B25: 14
B26: 15
B27: 16
B28: 17
B29: 18
B30: 19
C33: REQUERIMIENTOS FUNCIONALES DEL HISTORIAL DENTRO DE LA BASE DE DATOS
B36: 1
B37: 2
B38: 3
B39: 4
B40: 5
B41: 6
B42: 7
B43: 8
B44: 9
B45: 10
B46: 11
B47: 12

Sheet Finanzas NO FUN
B2: SI | C2: Marque con una equis (X) si el sistema no cumple con la función descrita | V2: Volver
B3: NO | C3: Marque con una equis (X) si el sistema cumple con la función descrita
B4: ADI | C4: Marque con una equis (X) si el sistema debe adicionar la función descrita
B5: Observaciones: | D5: Espacio para complementar respuestas
B7: P
M8: Nivel de cumplimiento | P8: OBSERVACIONES
C9: REQUERIMIENTOS NO FUNCIONALES DE LA GESTIÓN DE FINANZAS DENTRO DE LA PÁGINA WEB | M9: SI | N9: NO | O9: ADI
B12: 1 | C12: El título "Análisis Financiero..." debe usar el color institucional --welcome-blue (#36498f). | M12: x
B13: 2 | C13: El tamaño de fuente del título principal debe ser exactamente de 1.8rem. | M13: x
B14: 3 | C14: El contenedor principal de finanzas debe usar el color de fondo --bg-primary (#f5f7fa). | M14: x
B15: 4 | C15: El contenedor general debe tener un padding uniforme de 30px en todos sus lados. | M15: x
B16: 5 | C16: Al cargar el módulo, debe ejecutarse una animación fadeIn con una duración de 0.5s. | M16: x
B17: 6 | C17: El grupo de filtros (mes/año) debe tener bordes redondeados tipo píldora de 30px. | M17: x
B18: 7 | C18: Los selectores de fecha deben proyectar una sombra suave definida por la variable --card-shadow. | M18: x
B19: 8 | C19: El botón "Exportar Excel" debe usar un color verde sólido #087d4e con texto en blanco y negrita. | M19: x
B20: 9 | C20: Las tarjetas de KPI y gráficos deben tener un border-radius de 20px para un aspecto moderno. | M20: x
B21: 10 | C21: El icono de "Utilidad Neta" debe usar un color verde esmeralda para denotar éxito financiero. | M21: x
B22: 11 | C22: La tarjeta de "Tasa de Retorno" debe usar el color de advertencia naranja #f59e0b. | M22: x
B23: 12 | C23: El gráfico de medios de pago debe tener un diámetro de 200px con un hueco central de 140px. | M23: x
... B38: 27 | C38: Los archivos Excel generados no deben guardarse en el servidor, sino descargarse directamente al equipo del usuario para proteger la privacidad financiera. | M38: x
B39: 28
B40: 29
B41: 30
B42: 31
B43: 32
B44: 33
B45: 34

Sheet Historial FUN
B2: SI | C2: Marque con una equis (X) si el sistema no cumple con la función descrita | V2: Volver
B3: NO | C3: Marque con una equis (X) si el sistema cumple con la función descrita
B4: ADI | C4: Marque con una equis (X) si el sistema debe adicionar la función descrita
B5: Observaciones: | D5: Espacio para complementar respuestas
B7: P
M8: Nivel de cumplimiento | P8: OBSERVACIONES
C9: REQUERIMIENTOS FUNCIONALES DEL HISTORIAL DENTRO DE LA PÁGINA WEB | M9: SI | N9: NO | O9: ADI
B12: 1 | C12: El sistema debe mostrar el botón "<- Volver al Inicio" que redirecciona al dashboard principal. | M12: x
B13: 2 | C13: Al entrar a la sección de historial, el sistema debe mostrar el título "Historial de Movimientos", con el mensaje "Seleccione el tipo de historial que desea consultar.". | M13: x
B14: 3 | C14: El sistema debe desplegar una vista de tarjetas con el tipo de historial que maneja el sistema. | M14: x
B15: 4 | C15: Al dar click sobre una tarjeta el sistema debe abrir un nuevo menú correspondiente a la tarjeta que se seleccionó. | M15: x
B16: 5 | C16: Dentro de la tarjeta "Movimientos Materia Prima", debe existir una flecha "<-" para regresar a la sección de historial junto con un contador al otro extremo de la flecha, que muestre todos los registros actuales. | M16: x
B17: 6 | C17: Esta sección de historial de materia prima, debe contar con una barra de búsqueda predictiva, para buscar materia o proveedor, junto con filtros para seleccionar rangos del mes del año actual y para filtrar por fecha desde - hasta, funcionales. | M17: x
B18: 7 | C18: Los registros deben incluir un ícono indicativo del movimiento, su nombre, el proveedor, la fecha del movimiento, un indicativo con color según movimiento, indicador de cantidad por unidad de medida y sus observaciones. | M18: x
B19: 8 | C19: El sistema debe incluir un scroll funcional para los registros. | M19: x
B20: 9 | C20: El sistema debe permitir consultar el Historial de Compras de materia prima, filtrando por proveedor y rango de fechas. | M20: x
B21: 10 | C21: El sistema debe permitir consultar el Historial de Ventas (Facturación), filtrando por cliente, fecha o número de factura. | M21: x
B22: 11 | C22: El sistema debe mostrar una trazabilidad completa de un producto (Kardex): Cuándo se fabricó, cuándo se vendió y a quién. | M22: x
B23: 12 | C23: El módulo debe permitir ver el histórico de precios de venta de los productos del catálogo (Fluctuación de precios). | N23: x
B24: 13 | C24: El sistema debe permitir consultar el histórico de precios de compra de materia prima (Costos). | M24: x | R24: requerimiento de materia prima
B25: 14 | C25: El sistema debe permitir ver el historial de cambios en la información de un cliente (ej. cambios de dirección o teléfono). | N25: x
B26: 15 | C26: Al consultar un lote de producción, el sistema debe mostrar qué materias primas se consumieron en ese momento. | N26: x
B27: 17 | C27: El historial debe diferenciar visualmente entre movimientos de entrada (positivos) y salida (negativos). | M27: x
B28: 18 | C28: El sistema debe permitir la reimpresión o visualización de facturas antiguas desde el historial. | M28: x
B29: 19
C32: REQUERIMIENTOS FUNCIONALES DEL HISTORIAL DENTRO DE LA BASE DE DATOS
B35: 1 | C35: El sistema debe registrar automáticamente un histórico cuando se actualice el precio de una materia prima. | M35: x
B36: 2 | C36: La función de actualización de precio debe validar que el nuevo precio no sea negativo. | M36: x
B37: 3 | C37: El sistema debe exigir un "motivo" obligatorio (texto) para realizar el cambio de precio. | M37: x
B38: 4 | C38: La función debe recuperar automáticamente el precio anterior vigente para guardarlo en el registro histórico. | M38: x
B39: 5 | C39: Si no existe un historial previo, el sistema debe asumir el precio anterior como 0. | M39: x
B40: 6 | C40: El sistema debe impedir la actualización de precios para materias primas inactivas. | M40: x | R40: Mover de lugar a materias primas
B41: 7 | C41: El historial debe registrar la fecha y hora exacta del cambio de precio. | M41: x
B42: 10
B43: 11
B44: 12

Sheet Historial NO FUN.
B2: SI | C2: Marque con una equis (X) si el sistema no cumple con la función descrita | V2: Volver
B3: NO | C3: Marque con una equis (X) si el sistema cumple con la función descrita
B4: ADI | C4: Marque con una equis (X) si el sistema debe adicionar la función descrita
B5: Observaciones: | D5: Espacio para complementar respuestas
B7: P
M8: Nivel de cumplimiento | P8: OBSERVACIONES
C9: REQUERIMIENTOS NO FUNCIONALES DEL HISTORIAL DENTRO DE LA PÁGINA WEB | M9: SI | N9: NO | O9: ADI
B12: 1 | C12: (Navegación) El contenedor de selección debe usar display: grid con un ancho mínimo por tarjeta de 320px. | M12: x
B13: 2 | C13: Las tarjetas deben tener un box-shadow de 0 10px 30px var(--card-shadow) que cambie al hacer hover. | M13: x
B14: 3 | C14: Cada tarjeta debe incluir un borde inferior de 5px con el color institucional del área que representa. | M14: x
B15: 4 | C15: Los iconos de fondo en las tarjetas deben estar rotados y escalados con transform: translate(10%, 20%) y opacidad de 0.05. | M15: x
B16: 5 | C16: La vista raíz debe cargar con la clase kardex-slide-in-up (duración 0.5s). | M16: x
B17: 6 | C17: Al cargar cualquier historial, el sistema debe eliminar automáticamente cualquier Botón de Acción Flotante (FAB) residual de otros módulos. | M17: x
B18: 7 | C18: Los nombres de las tarjetas deben usar var(--text-main) para asegurar legibilidad en modo claro y oscuro. | M18: x
B19: 8 | C19: (Bodega Inicial) El borde de acento y los títulos de Bodega deben usar el azul oscuro --welcome-blue (#36498f). | M19: x
B20: 9 | C20: El botón de "atrás" debe tener un degradado de azul a verde y forma circular (40x40px). | M20: x
B21: 10 | C21: Los encabezados (th) deben ser blancos con texto negro y borde inferior sutil (rgba(0,0,0,0.1)). | M21: x
B22: 11 | C22: La tabla de bodega debe tener un max-height de 60vh con overflow-y: auto. | M22: x
B23: 12 | C23: Cada registro de fecha debe ir acompañado del icono fa-regular fa-clock en color gris mutado. | M23: x
... B62: 51 | C62: El botón de "Desechar" debe usar el color gris neutro (#6b7280). | M62: x
B63: 52 | C63: Al "Reparar", el sistema debe enviar un comando SQL que incremente el stock del producto original. | M63: x | R63: req funcional
B64: 53 | C64: Al "Desechar", el registro se marca como resuelto pero no altera las cantidades del inventario. | M64: x | R64: req funcional
B65: 54 | C65: La tabla debe recargarse inmediatamente después de cada resolución exitosa. | M65: x
B66: 55 | C66: (Visualización de Factura) La factura debe cargarse siempre en una nueva ventana del navegador para no perder el contexto del historial. | M66: x
B67: 56 | C67: Se debe enviar el id_factura de forma limpia para que el generador PHP la reconozca. | M67: x
B68: 57 | C68: El botón "Ver Factura" debe tener un icono de fa-file-invoice y fondo verde oscuro. | M68: x
B69: 58 | C69: La cabecera de la factura debe incluir un borde superior con un degradado lineal (linear-gradient) de azul institucional (#36498f) a verde esmeralda (#087d4e). | M69: x
B70: 59 | C70: El título principal "FACTURA COMERCIAL" debe usar el color verde (#087d4e) en negrita y alineación derecha. | M70: x
B71: 60 | C71: Los datos informativos de la empresa (Dirección, Teléfono, Email) deben usar un color gris neutro (#666) con iconos de FontAwesome alineados. | M71: x
B72: 61 | C72: Los encabezados de sección ("FACTURADO A:", "INFORMACIÓN DE PAGO:") deben estar en mayúsculas, color gris y con una línea divisoria inferior de 1px. | M72: x
B73: 62 | C73: Los nombres de clientes y métodos de pago deben resaltar en color azul oscuro/negro (#333) y peso de fuente 700. | M73: x
B74: 63 | C74: El encabezado de la tabla de productos debe tener un fondo azul oscuro (#36498f) con texto en blanco para alto contraste. | M74: x
B75: 64 | C75: Las columnas de cantidad, precio y total deben estar alineadas a la derecha o centro para facilitar la lectura de cifras. | M75: x
B76: 65 | C76: El desglose de "Contenido del Kit" debe aparecer dentro de un recuadro con un borde izquierdo de 3px color verde y fondo gris muy tenue. | M76: x
... B91: 80 | C91: Se debe usar un spinner de FontAwesome (fa-spinner fa-spin) de tamaño 2x o 4x durante la espera de datos. | M91: x
C110: REQUERIMIENTOS NO FUNCIONALES DEL HISTORIAL DENTRO DE LA BASE DE DATOS
B113: 1 | C113: Los registros históricos deben ser inmutables (de solo lectura) una vez creados. | M113: x | R113: Mover a materia prima
B114: 2 | C114: El sistema debe conservar el historial de precios por un periodo indefinido para análisis de costos. | M114: x | R114: Mover a materia prima
B115: 3
B116: 4
B117: 5
B118: 6
B119: 7
B120: 8
B121: 9
B122: 10

Sheet Clientes FUN
B2: SI | C2: Marque con una equis (X) si el sistema no cumple con la función descrita | V2: Volver
B3: NO | C3: Marque con una equis (X) si el sistema cumple con la función descrita
B4: ADI | C4: Marque con una equis (X) si el sistema debe adicionar la función descrita
B5: Observaciones: | D5: Espacio para complementar respuestas
B7: P
M8: Nivel de cumplimiento | P8: OBSERVACIONES
D9: REQUERIMIENTOS FUNCIONALES DE CLIENTES DENTRO DE LA PÁGINA WEB | M9: SI | N9: NO | O9: ADI
B12: 1
B13: 2
B14: 3
B15: 4
B16: 5
B17: 6
C20: REQUERIMIENTOS FUNCIONALES DE CLIENTES DENTRO DE LA BASE DE DATOS
B23: 1 | C23: El sistema debe validar que el número de documento del cliente no sea nulo al momento del registro. | M23: x
B24: 2 | C24: La función de clientes debe impedir la creación de registros duplicados basados en el número de documento. | N24: x | R24: NO SIRVE
B25: 3 | C25: El sistema debe validar que el primer nombre y primer apellido del cliente sean obligatorios. | M25: x
B26: 4 | C26: El sistema debe permitir registrar un segundo nombre y segundo apellido como campos opcionales. | M26: x
B27: 5 | C27: La función de inserción debe validar que la ciudad asociada al cliente exista en la tabla tab_ciudades. | N27: x | R27: revisar
B28: 6 | C28: El sistema debe validar que el tipo de documento asociado exista en tab_tipo_documentos. | M28: x | R28: revisar
B29: 7 | C29: El sistema debe impedir que se ingrese un teléfono de cliente con valores negativos o cero. | M29: x
B30: 8 | C30: La función de actualización debe permitir modificar la dirección y teléfono del cliente sin alterar su historial de facturación. | N30: x | R30: realizar pruebas
B31: 9 | C31: El sistema debe inicializar el campo de "Puntos de Fidelización" en 0 al crear un nuevo cliente. | M31: x
B32: 10 | C32: La eliminación de un cliente debe ser lógica, cambiando su estado a inactivo para no perder historial de ventas. | M32: x
B33: 11
B34: 12
B35: 13

Sheet Clientes NO FUN.
B2: SI | C2: Marque con una equis (X) si el sistema no cumple con la función descrita | V2: Volver
B3: NO | C3: Marque con una equis (X) si el sistema cumple con la función descrita
B4: ADI | C4: Marque con una equis (X) si el sistema debe adicionar la función descrita
B5: Observaciones: | D5: Espacio para complementar respuestas
B7: P
M8: Nivel de cumplimiento | P8: OBSERVACIONES
C9: REQUERIMIENTOS NO FUNCIONALES DE CLIENTES DENTRO DE LA PÁGINA WEB | M9: SI | N9: NO | O9: ADI
B12: 1
B13: 2
B14: 3
B15: 4
B16: 5
B17: 6
C20: REQUERIMIENTOS NO FUNCIONALES DE CLIENTES DENTRO DE LA BASE DE DATOS
B23: 1 | C23: La búsqueda de clientes por número de documento debe retornar resultados en menos de 1 segundo. | N23: x
B24: 2 | C24: El campo de dirección del cliente debe soportar hasta 200 caracteres para direcciones detalladas. | M24: x
B25: 3 | C25: El sistema debe validar que los nombres y apellidos contengan solo caracteres alfabéticos (incluyendo tildes y ñ). | M25: x | R25: revisar
B26: 4 | C26: La base de datos debe tener un índice en el campo num_documento para optimizar la búsqueda en el punto de venta. | N26: x
B27: 5 | C27: Los mensajes de error al gestionar clientes deben ser descriptivos para el usuario final (ej. "El cliente ya existe"). | M27: x
B28: 6
B29: 7
B30: 8
B31: 9
B32: 10
B33: 11
B34: 12
B35: 13

Sheet Facturación FUN.
B2: SI | C2: Marque con una equis (X) si el sistema no cumple con la función descrita | V2: Volver
B3: NO | C3: Marque con una equis (X) si el sistema cumple con la función descrita
B4: ADI | C4: Marque con una equis (X) si el sistema debe adicionar la función descrita
B5: Observaciones: | D5: Espacio para complementar respuestas
B7: P
M8: Nivel de cumplimiento | P8: OBSERVACIONES
C9: REQUERIMIENTOS FUNCIONALES DE FACTURACIÓN DENTRO DE LA PÁGINA WEB | M9: SI | N9: NO | O9: ADI
B12: 1
B13: 2
B14: 3
B15: 4
B16: 5
B17: 6
C20: REQUERIMIENTOS FUNCIONALES DE FACTURACIÓN DENTRO DE LA BASE DE DATOS
B23: 1 | C23: La función de facturación debe recibir la lista de productos y cantidades como arreglos (Arrays) de datos. | M23: x
B24: 2 | C24: El sistema debe validar que la cantidad de productos coincida con la cantidad de ítems en el arreglo de cantidades. | M24: x
B25: 3 | C25: El sistema debe impedir la facturación a clientes que se encuentren en estado inactivo (ind_vivo = FALSE). | M25: x
B26: 4 | C26: La función debe validar que el consecutivo de facturación actual no supere el rango final autorizado en tab_parametros. | M26: x
B27: 5 | C27: El sistema debe calcular automáticamente el valor bruto, descuento y neto para cada ítem de la factura. | M27: x
B28: 6 | C28: La base de datos debe identificar si el producto es un "Kit" o un "Instrumento" para descontar del inventario correcto. | M28: x
B29: 7 | C29: El sistema debe actualizar (incrementar) automáticamente el consecutivo de facturación tras una venta exitosa. | M29: x
B30: 8 | C30: La función debe registrar la fecha y hora exacta (NOW()) de la transacción de venta. | M30: x
B31: 9 | C31: El sistema debe acumular puntos de fidelización al cliente basados en el total de la factura. | N31: x | R31: revisar
B32: 10 | C32: El sistema debe realizar un ROLLBACK total de la transacción si falla la inserción de cualquier detalle de la factura. | M32: x | R32: Raise exception
B33: 11
B34: 12
B35: 13

Sheet Facturación NO FUN.
B2: SI | C2: Marque con una equis (X) si el sistema no cumple con la función descrita | V2: Volver
B3: NO | C3: Marque con una equis (X) si el sistema cumple con la función descrita
B4: ADI | C4: Marque con una equis (X) si el sistema debe adicionar la función descrita
B5: Observaciones: | D5: Espacio para complementar respuestas
B7: P
M8: Nivel de cumplimiento | P8: OBSERVACIONES
C9: REQUERIMIENTOS NO FUNCIONALES DE FACTURACIÓN DENTRO DE LA PÁGINA WEB | M9: SI | N9: NO | O9: ADI
B12: 1
B13: 2
B14: 3
B15: 4
B16: 5
B17: 6
C20: REQUERIMIENTOS NO FUNCIONALES DE FACTURACIÓN DENTRO DE LA BASE DE DATOS
B23: 1 | C23: El proceso completo de facturación (cabecera + detalles + kardex) debe completarse en menos de 3 segundos. | M23: x | R23: realizar pruebas
B24: 2 | C24: El sistema debe garantizar la consistencia de los datos financieros (sin decimales erróneos) usando tipos de datos DECIMAL. | N24: x | R24: revisar
B25: 3 | C25: La función de facturación debe ser capaz de procesar facturas con hasta 50 ítems sin degradación de rendimiento. | N25: x | R25: Y si son varios? Solo deja facturar 1 | V25: Realizar el mismo mecanismo de crear kits
B26: 4 | C26: El sistema de facturación debe estar disponible 99.9% del tiempo operativo. | N26: x
B27: 5 | C27: Los cálculos de totales deben tener una precisión de 2 decimales. | M27: x
B28: 6
B29: 7
B30: 8
B31: 9
B32: 10
B33: 11
B34: 12
B35: 13

Sheet Gestión Usuarios FUN.
B2: SI | C2: Marque con una equis (X) si el sistema no cumple con la función descrita | V2: Volver
B3: NO | C3: Marque con una equis (X) si el sistema cumple con la función descrita
B4: ADI | C4: Marque con una equis (X) si el sistema debe adicionar la función descrita
B5: Observaciones: | D5: Espacio para complementar respuestas
B7: P
M8: Nivel de cumplimiento | P8: OBSERVACIONES
C9: REQUERIMIENTOS FUNCIONALES DE GESTIÓN USUARIOS DENTRO DE LA PÁGINA WEB | M9: SI | N9: NO | O9: ADI
B12: 1
B13: 2
B14: 3
B15: 4
B16: 5
B17: 6
C20: REQUERIMIENTOS FUNCIONALES DE GESTIÓN USUARIOS DENTRO DE LA BASE DE DATOS
B23: 1 | C23: La función de creación de usuarios debe validar que el nombre de usuario no contenga espacios vacíos. | M23: x
B24: 2 | C24: El sistema debe impedir el registro de dos usuarios con el mismo correo electrónico. | N24: x | R24: realizar pruebas
B25: 3 | C25: El sistema debe validar que el número de teléfono del usuario tenga exactamente 10 dígitos numéricos. | N25: x
B26: 4 | C26: La función de actualización de usuarios debe verificar que el usuario exista y esté activo (ind_vivo = TRUE) antes de modificarlo. | M26: x
B27: 5 | C27: El sistema debe permitir actualizar la contraseña del usuario validando la complejidad requerida. | M27: x | R27: revisar
B28: 6 | C28: El sistema debe validar que el correo electrónico del usuario tenga un formato válido (contenga '@' y dominio). | M28: x | R28: revisar
B29: 7 | C29: El sistema debe impedir la creación de usuarios si el número de teléfono ya está asociado a otra cuenta activa. | N29: x
B30: 8 | C30: La función de inserción de usuarios debe asignar automáticamente un ID único consecutivo. | M30: x
B31: 9 | C31: El sistema debe retornar un mensaje de error específico ("Usuario ya existe", "Email inválido") según el fallo de validación. | M31: x
B32: 10 | C32: La gestión de usuarios debe permitir la asignación de roles o perfiles (asociado a Permisos). | N32: x
B33: 11
B34: 12
B35: 13

Sheet Gestión Usuarios NO FUN.
B2: SI | C2: Marque con una equis (X) si el sistema no cumple con la función descrita | V2: Volver
B3: NO | C3: Marque con una equis (X) si el sistema cumple con la función descrita
B4: ADI | C4: Marque con una equis (X) si el sistema debe adicionar la función descrita
B5: Observaciones: | D5: Espacio para complementar respuestas
B7: P
M8: Nivel de cumplimiento | P8: OBSERVACIONES
C9: REQUERIMIENTOS NO FUNCIONALES DE GESTIÓN USUARIOS DENTRO DE LA PÁGINA WEB | M9: SI | N9: NO | O9: ADI
B12: 1
B13: 2
B14: 3
B15: 4
B16: 5
B17: 6
C20: REQUERIMIENTOS NO FUNCIONALES DE GESTIÓN USUARIOS DENTRO DE LA BASE DE DATOS
B23: 1 | C23: Las contraseñas de los usuarios no deben almacenarse en texto plano, deben estar encriptadas (ej. Hash SHA-256 o bcrypt). | M23: x
B24: 2 | C24: La validación de credenciales de usuario debe ejecutarse en menos de 500 milisegundos. | N24: x | R24: realizar pruebas
B25: 3 | C25: El campo de contraseña en la base de datos debe tener longitud suficiente para almacenar el hash encriptado. | M25: x
B26: 4 | C26: La función de gestión de usuarios debe ser resistente a inyecciones SQL mediante el uso de parámetros tipados. | N26: x | R26: realizar pruebas
B27: 5 | C27: El sistema debe garantizar la confidencialidad de los datos de contacto (teléfono y correo) del usuario. | N27: x
B28: 6
B29: 7
B30: 8
B31: 9
B32: 10
B33: 11
B34: 12
B35: 13

Sheet Permisos y Menús FUN.
B2: SI | C2: Marque con una equis (X) si el sistema no cumple con la función descrita | V2: Volver
B3: NO | C3: Marque con una equis (X) si el sistema cumple con la función descrita
B4: ADI | C4: Marque con una equis (X) si el sistema debe adicionar la función descrita
B5: Observaciones: | D5: Espacio para complementar respuestas
B7: P
M8: Nivel de cumplimiento | P8: OBSERVACIONES
C9: REQUERIMIENTOS FUNCIONALES DE PERMISOS DENTRO DE LA PÁGINA WEB | M9: SI | N9: NO | O9: ADI
B12: 1
B13: 2
B14: 3
B15: 4
B16: 5
B17: 6
C20: REQUERIMIENTOS FUNCIONALES DE PERMISOS DENTRO DE LA BASE DE DATOS
B23: 1 | C23: El sistema debe permitir asignar menús específicos a usuarios específicos. | M23: x
B24: 2 | C24: La base de datos debe validar que el usuario y el menú existan antes de crear la asociación. | N24: x | R24: revisar
B25: 3 | C25: El sistema debe permitir revocar el acceso de un usuario a un menú (Eliminación lógica o física de la relación). | N25: x
B26: 4 | C26: La consulta de menús debe retornar solo las opciones activas (ind_vivo = TRUE). | M26: x
B27: 5 | C27: El sistema debe validar que el nombre del programa (nom_prog) asociado al menú no sea nulo. | N27: x
B28: 6 | C28: La base de datos debe impedir asignar el mismo menú dos veces al mismo usuario (Clave primaria compuesta). | N28: x | R28: revisar
B29: 7 | C29: El sistema debe permitir crear nuevos ítems de menú dinámicamente. | N29: x
B30: 8 | C30: Al cargar el sistema, se deben obtener solo los menús autorizados para el usuario que inició sesión. | N30: x
B31: 9 | C31: La estructura debe permitir jerarquías de menús si se requiere (aunque el modelo actual es plano, la lógica debe permitirlo). | N31: x
B32: 10 | C32: El sistema de auditoría debe registrar quién asignó o revocó permisos a un usuario. | N32: x | R32: revisar
B33: 11
B34: 12
B35: 13

Sheet Permisos y Menús NO FUN.
B2: SI | C2: Marque con una equis (X) si el sistema no cumple con la función descrita | V2: Volver
B3: NO | C3: Marque con una equis (X) si el sistema cumple con la función descrita
B4: ADI | C4: Marque con una equis (X) si el sistema debe adicionar la función descrita
B5: Observaciones: | D5: Espacio para complementar respuestas
B7: P
M8: Nivel de cumplimiento | P8: OBSERVACIONES
C9: REQUERIMIENTOS NO FUNCIONALES DE PERMISOS DENTRO DE LA PÁGINA WEB | M9: SI | N9: NO | O9: ADI
B12: 1
B13: 2
B14: 3
B15: 4
B16: 5
B17: 6
C20: REQUERIMIENTOS NO FUNCIONALES DE PERMISOS DENTRO DE LA BASE DE DATOS
B23: 1 | C23: La validación de permisos debe ser inmediata al intentar acceder a un módulo. | N23: x
B24: 2 | C24: La estructura de permisos debe ser flexible para agregar nuevos módulos sin reestructurar la base de datos. | N24: x
B25: 3 | C25: El sistema no debe mostrar opciones de menú deshabilitadas o inactivas para evitar confusión. | N25: x
B26: 4 | C26: La consulta de permisos debe ser de alta velocidad ya que se ejecuta en cada inicio de sesión o navegación. | N26: x
B27: 5 | C27: La seguridad de acceso debe validarse tanto en el Frontend (visibilidad) como en el Backend (acceso a datos). | N27: x
B28: 6
B29: 7
B30: 8
B31: 9
B32: 10
B33: 11
B34: 12
B35: 13

Sheet INVENTARIO TRANSACCIONAL
B2: Funciones insert | F2: Funciones update | J2: Funciones delete | N2: Funciones transaccionales | T2: Volver
B4: - fun_insert_banco_prov.sql | F4: - fun_update_banco_prov.sql | J4: - fun_delete_banco_prov.sql | N4: fun_act_precio.sql (Actualiza precios de historico materia prima)
B5: - fun_insert_bancos.sql | F5: - fun_update_bancos.sql | J5: - fun_delete_bancos.sql | N5: fun_caja_diario.sql (Cálculo y cierre de caja diaria)
B6: - fun_insert_cargo.sql | F6: - fun_update_cargos.sql | J6: - fun_delete_cargos.sql | N6: fun_fact.sql (Función principal de facturación general) | Q6: Implementada
B7: - fun_insert_cat_mat.sql | F7: - fun_update_cat_mat_prim.sql | J7: - fun_delete_cat_mat_prim.sql | N7: fun_kardex_mat_prim.sql (Gestión de movimientos de inventario de materia prima) | Q7: Implementada
B8: - fun_insert_ciudades.sql | F8: - fun_update_ciudades.sql | J8: - fun_delete_ciudades.sql | N8: fun_kardex_prod.sql (Gestión de movimientos de inventario de producto terminado) | Q8: Implementada
B9: - fun_insert_cliente.sql | F9: - fun_update_clientes.sql | J9: - fun_delete_clientes.sql | N9: fun_listar_fact.sql (Listado de facturas) | Q9: ?
B10: - fun_insert_departamento.sql | F10: - fun_update_departamentos.sql | J10: - fun_delete_departamentos.sql
B11: - fun_insert_devolucion.sql | F11: - fun_update_detalle_factura.sql | J11: - fun_delete_detalle_factura.sql
B12: - fun_insert_empleados.sql | F12: - fun_update_devolucion.sql | J12: - fun_delete_devolucion.sql
B13: - fun_insert_especializacion.sql | F13: - fun_update_empleados.sql | J13: - fun_delete_empleados.sql
B14: - fun_insert_estado_fact.sql | F14: - fun_update_estado_fact.sql | J14: - fun_delete_estado_fact.sql
B15: - fun_insert_instrumento_kit.sql | F15: - fun_update_facturas.sql | J15: - fun_delete_factura_completa.sql
B16: - fun_insert_instrumentos (añadir_validacion).sql | F16: - fun_update_historico_mat_prima.sql | J16: - fun_delete_historico_mat_prima.sql
B17: - fun_insert_kits.sql | F17: - fun_update_instrumentos(añadir_validaciones).sql | J17: - fun_delete_instrumentos.sql
B18: - fun_insert_mat_prima_proveedor.sql | F18: - fun_update_kardex_mat_prima.sql | J18: - fun_delete_instrumentos_kit.sql
B19: - fun_insert_materia_primas.sql | F19: - fun_update_kardex_productos.sql | J19: - fun_delete_kardex_mat_prima.sql
B20: - fun_insert_menu.sql | F20: - fun_update_kit.sql | J20: - fun_delete_kardex_productos.sql
B21: - fun_insert_menu_user.sql | F21: - fun_update_mat_prima_proveedor.sql | J21: - fun_delete_kit.sql
... B26: - fun_insert_user.sql | F26: - fun_update_movimiento_bodega.sql | J26: - fun_delete_movimiento_a_produccion.sql
F27: - fun_update_parametros.sql | J27: - fun_delete_movimiento_bodega.sql
F28: - fun_update_producto.sql | J28: - fun_delete_producto.sql
F29: - fun_update_proveedores.sql | J29: - fun_delete_proveedores.sql
F30: - fun_update_tab_instrumentos_kit.sql | J30: - fun_delete_tipo_documento.sql
F31: - fun_update_tipo_documentos.sql | J31: - fun_delete_tipo_especializacion.sql
F32: - fun_update_tipo_especializacion.sql | J32: - fun_delete_tipo_sangre.sql
F33: - fun_update_tipo_sangre.sql | J33: - fun_delete_user.sql
F34: - fun_update_user.sql
B39: Transaccion - Carga del sistema
